Workbook

Sheet 📋 Index
B1: PORTFOLIO MASTER FILE — HU3110
B2: HU3110 · Zerodha Demat · Update prices: 📥 Price Hub col H → all sheets recalculate
B5: TOTAL INVESTED | D5: MARKET VALUE | F5: RETURN | G5: UNREALISED P&L
B6: {='📊 Portfolio Brief'!G40} -> 8790005.6 | D6: {='📊 Portfolio Brief'!H40} -> 10119824 | F6: 15.1% | G6: {='📊 Portfolio Brief'!I40/'📊 Portfolio Brief'!G40} -> 0.15128753
G7: {='📊 Portfolio Brief'!I40} -> 1329818.3
B10: HU3110 · PORTFOLIO MASTER FILE · Zerodha Demat · 6 March 2026
B11: ₹87.9L invested · ₹1.01Cr market value · +15.1% return · 29 holdings · Consolidating to 20
B13: TAB | C13: LAYER | D13: CONTENTS
B14: PORTFOLIO
B15: 📋 Index | C15: PORTFOLIO | D15: This sheet — overview, portfolio metrics, tab directory.
B16: 📥 Price Hub | C16: PORTFOLIO | D16: ⭐ START HERE for price updates. Update col H (CMP) — all sheets recalculate. Static: Qty/AvgCost/LT Qty (trade only).
B17: 📡 LLM Context | C17: PORTFOLIO | D17: ⭐ START HERE for any review session. Full portfolio state — 27 stocks, live P&L, action codes, catalyst + next trigger. ~350 tokens. Read this before any other sheet.
B18: 📊 Portfolio Brief | C18: PORTFOLIO | D18: All 29 holdings with thesis notes, action tags, P&L.
B19: ⚡ Action Summary | C19: PORTFOLIO | D19: Working checklist — Accumulate / Trim / Hold / Watch.
B20: 🔬 Priority Research | C20: PORTFOLIO | D20: Top 5 + Zydus validation. Live web research. 6 Mar update.
B21: 🗺️ Portfolio Roadmap | C21: PORTFOLIO | D21: Merged: Road to 20 + Consolidation Plan. Wave 1 exits/trims, execution sequence, target 20 portfolio, capital redeployment, Wave 2 flags.
B22: 🔀 Consolidation Plan | C22: PORTFOLIO | D22: v2. BANKBARODA kept. NH sized up. IEX accumulation.
B23: ⚠️ Risk Flags
B24: 🎯 Scenario Analysis
B25: SECTORAL
B26: 🏭 Sector Analysis
B27: 💻 IT Sector Analysis
B28: INDIVIDUAL STOCKS
B29: ⚡ IEX Deep Dive | C29: INDIVIDUAL | D29: ACCUMULATING. Coupling mispriced on timing. Vol +30% YoY. 2.5% yield.
B30: 🔍 IT Deep Dive | C30: INDIVIDUAL | D30: Persistent · eClerx · Sagility — AI disruption, bull/base/bear.
B31: 💊 Medi Assist | C31: INDIVIDUAL | D31: Accumulate. MIT ₹535 anchor. IRDAI cleared ✅. Technical: approaching zone.
B32: 📈 MEDIASSIST Technical | C32: INDIVIDUAL | D32: Chart structure, key levels, 5-tranche entry plan.
B33: 🧨 Chambal Fert | C33: INDIVIDUAL | D33: Hold. TAN April 2026 commissioning confirmed. Wait.
B34: 🏢 EID Parry | C34: INDIVIDUAL | D34: Hold patient. Coromandel 50–60% holdco discount.
B35: 🏦 Utkarsh SFB
B37: Updated 6 Mar 2026 · Research from live web data, company filings, Q3 FY26 earnings ·
B74: 🤖 LLM OPERATING INSTRUCTIONS — Read this first. Determines what to load each session.
B75: SINGLE SOURCE OF TRUTH | C75: 📥 Price Hub col H = CMP. All Mkt Val, P&L, Ret%, Wt% derive from this via formulas. NEVER manually edit calculated fields in other sheets. Writable fields: Price Hub col H (CMP always), col D/E/F (Qty/AvgCost/LTQty on trades only), col M/N (52W H/L optional).
B76: MINIMUM READ SETS | C76: ① PRICE UPDATE: Open 📥 Price Hub → update col H only. ~50 tokens. Done. ② PORTFOLIO REVIEW: Read 📡 LLM Context (~350 tokens) + glance at Price Hub. Optionally ⚡ Action Summary. ③ STOCK DEEP DIVE: Read 📡 LLM Context + that stock's Deep Dive tab only. ④ FULL SESSION: 📡 LLM Context → ⚡ Action Summary → 🔬 Priority Research → stock tabs as needed. ⛔ SKIP UNLESS ASKED: 🗺️ Portfolio Roadmap, , 🎯 Scenario Analysis.
B77: WRITE PROTOCOL | C77: After thesis/action changes: (a) update 📡 LLM Context col ACTION + NOTES for affected stocks, (b) update 📊 Portfolio Brief Notes col, (c) append one row to 📝 Changelog with date + change summary. After price update: verify one spot-check stock in Portfolio Brief shows updated Mkt Val before closing.
B78: SHEET TAXONOMY | C78: 🟡 LIVE — update every session: 📥 Price Hub · 📡 LLM Context · 📝 Changelog 🔵 REFERENCE — update on thesis change: 📊 Portfolio Brief · ⚡ Action Summary · ⚠️ Risk Flags · 🔬 Priority Research ⚪ ARCHIVE — read-once, rarely updated: Portfolio Roadmap · Scenario Analysis · Sector Analysis · Deep Dive tabs

Sheet 📥 Price Hub
B1: 📥 PRICE HUB — Single source of truth | Update CMP here → all sheets recalculate
B2: 🟡 YELLOW = Update these · 🟢 GREEN = Auto-calculated · ⬜ WHITE = Static (update only when you trade) · Last updated: 7 Mar 2026
B4: SYMBOL | C4: SUB-SECTOR | D4: TOTAL QTY | E4: AVG COST ₹ | F4: LT QTY | G4: NON-LT QTY | H4: ⬇ CMP ₹ (UPDATE HERE) | I4: MKT VAL ₹ | J4: INVESTED ₹ | K4: P&L ₹ | L4: RET % | M4: 52W HIGH | N4: 52W LOW | O4: % FROM 52W H | P4: NOTES / DATE
B5: GOLDIETF-E | C5: ETF | D5: 8000 | E5: 84.4748 | F5: 0 | G5: {=D5-F5} -> 8000 | H5: 138.3 | I5: {=D5*H5} -> 1106400 | J5: {=D5*E5} -> 675798.4 | K5: {=I5-J5} -> 430601.6 | L5: {=IF(J5=0,"-",I5/J5-1)} -> 0.63717464 | O5: {=IF(M5="","",H5/M5-1)} | P5: CMP as of 5 Mar 2026
B6: BAJFINANCE | C6: CONSUMER LENDING | D6: 750 | E6: 660 | F6: 0 | G6: {=D6-F6} -> 750 | H6: 945.1 | I6: {=D6*H6} -> 708825 | J6: {=D6*E6} -> 495000 | K6: {=I6-J6} -> 213825 | L6: {=IF(J6=0,"-",I6/J6-1)} -> 0.4319697 | O6: {=IF(M6="","",H6/M6-1)} | P6: CMP as of 5 Mar 2026
B7: UJJIVANSFB | C7: MICROFINANCE | D7: 10074 | E7: 41.8047 | F7: 0 | G7: {=D7-F7} -> 10074 | H7: 54.27 | I7: {=D7*H7} -> 546715.98 | J7: {=D7*E7} -> 421140.55 | K7: {=I7-J7} -> 125575.43 | L7: {=IF(J7=0,"-",I7/J7-1)} -> 0.29817939 | O7: {=IF(M7="","",H7/M7-1)} | P7: CMP as of 5 Mar 2026
B8: COALINDIA | C8: METALS | D8: 1200 | E8: 388.9194 | F8: 0 | G8: {=D8-F8} -> 1200 | H8: 435.15 | I8: {=D8*H8} -> 522180 | J8: {=D8*E8} -> 466703.28 | K8: {=I8-J8} -> 55476.72 | L8: {=IF(J8=0,"-",I8/J8-1)} -> 0.11886936 | O8: {=IF(M8="","",H8/M8-1)} | P8: CMP as of 5 Mar 2026
B9: ICICIBANK | C9: BANKING | D9: 375 | E9: 1154.2536 | F9: 350 | G9: {=D9-F9} -> 25 | H9: 1365.4 | I9: {=D9*H9} -> 512025 | J9: {=D9*E9} -> 432845.1 | K9: {=I9-J9} -> 79179.9 | L9: {=IF(J9=0,"-",I9/J9-1)} -> 0.18292895 | O9: {=IF(M9="","",H9/M9-1)} | P9: CMP as of 5 Mar 2026
B10: HOMEFIRST | C10: HOUSING FINANCE | D10: 441 | E10: 934.6512 | F10: 441 | G10: {=D10-F10} -> 0 | H10: 1074.4 | I10: {=D10*H10} -> 473810.4 | J10: {=D10*E10} -> 412181.18 | K10: {=I10-J10} -> 61629.221 | L10: {=IF(J10=0,"-",I10/J10-1)} -> 0.14951974 | O10: {=IF(M10="","",H10/M10-1)} | P10: CMP as of 5 Mar 2026
B11: CARYSIL | C11: FMCG | D11: 550 | E11: 743.8698 | F11: 425 | G11: {=D11-F11} -> 125 | H11: 859.1 | I11: {=D11*H11} -> 472505 | J11: {=D11*E11} -> 409128.39 | K11: {=I11-J11} -> 63376.61 | L11: {=IF(J11=0,"-",I11/J11-1)} -> 0.15490641 | O11: {=IF(M11="","",H11/M11-1)} | P11: CMP as of 5 Mar 2026
B12: BANKBARODA | C12: BANKING | D12: 1500 | E12: 241.5191 | F12: 0 | G12: {=D12-F12} -> 1500 | H12: 299.3 | I12: {=D12*H12} -> 448950 | J12: {=D12*E12} -> 362278.65 | K12: {=I12-J12} -> 86671.35 | L12: {=IF(J12=0,"-",I12/J12-1)} -> 0.23923946 | O12: {=IF(M12="","",H12/M12-1)} | P12: CMP as of 5 Mar 2026
B13: CREDITACC | C13: MICROFINANCE | D13: 350 | E13: 961.5244 | F13: 275 | G13: {=D13-F13} -> 75 | H13: 1225.8 | I13: {=D13*H13} -> 429030 | J13: {=D13*E13} -> 336533.54 | K13: {=I13-J13} -> 92496.46 | L13: {=IF(J13=0,"-",I13/J13-1)} -> 0.27485064 | O13: {=IF(M13="","",H13/M13-1)} | P13: CMP as of 5 Mar 2026
B14: LT | C14: ENGINEERING & CAPITAL GOODS | D14: 110 | E14: 3614.1977 | F14: 0 | G14: {=D14-F14} -> 110 | H14: 3882.6 | I14: {=D14*H14} -> 427086 | J14: {=D14*E14} -> 397561.75 | K14: {=I14-J14} -> 29524.253 | L14: {=IF(J14=0,"-",I14/J14-1)} -> 0.074263314 | O14: {=IF(M14="","",H14/M14-1)} | P14: CMP as of 5 Mar 2026
B15: NH | C15: HEALTHCARE | D15: 240 | E15: 1336.4402 | F15: 200 | G15: {=D15-F15} -> 40 | H15: 1744 | I15: {=D15*H15} -> 418560 | J15: {=D15*E15} -> 320745.65 | K15: {=I15-J15} -> 97814.352 | L15: {=IF(J15=0,"-",I15/J15-1)} -> 0.30495925 | O15: {=IF(M15="","",H15/M15-1)} | P15: CMP as of 5 Mar 2026
B16: HDFCBANK | C16: BANKING | D16: 450 | E16: 626.6593 | F16: 175 | G16: {=D16-F16} -> 275 | H16: 868.65 | I16: {=D16*H16} -> 390892.5 | J16: {=D16*E16} -> 281996.68 | K16: {=I16-J16} -> 108895.82 | L16: {=IF(J16=0,"-",I16/J16-1)} -> 0.38615991 | O16: {=IF(M16="","",H16/M16-1)} | P16: CMP as of 5 Mar 2026
... B31: SGB-COMBINED | C31: SOVEREIGN GOLD BOND | D31: 6 | E31: 16262.96 | F31: 0 | G31: {=D31-F31} -> 6 | H31: 16392.83 | I31: {=D31*H31} -> 98356.98 | J31: {=D31*E31} -> 97577.76 | K31: {=I31-J31} -> 779.22 | L31: {=IF(J31=0,"-",I31/J31-1)} -> 0.0079856312 | O31: {=IF(M31="","",H31/M31-1)} | P31: 2 SGBs: 4 units Dec-2031 + 2 units Apr-2028. Tax-free capital gains at maturity. Zero action.
B34: TOTAL | I34: {=SUM(I5:I33)} -> 10119824 | J34: {=SUM(J5:J33)} -> 8790005.6 | K34: {=SUM(K5:K33)} -> 1329818.3 | L34: {=I34/J34-1} -> 0.15128753

Sheet 📡 LLM Context
B1: 📡 LLM CONTEXT — Full portfolio state in one read | ~350 tokens | Formula-linked to Price Hub
B2: 🟢 GREEN = ACCUMULATE | 🟡 AMBER = TRIM | 🔵 BLUE = HOLD | 🟠 ORANGE = WATCH | 🟣 PURPLE = RE-ENTRY | Mkt Val, P&L, Ret% update automatically when Price Hub CMP changes
B4: SYM | C4: SECTOR | D4: ACTION | E4: WT% | F4: CMP ₹ | G4: AVG ₹ | H4: RET% | I4: MKT VAL ₹ | J4: P&L ₹ | K4: QTY | L4: LT QTY | M4: KEY CATALYST / THESIS | N4: NEXT TRIGGER / WATCH
B5: GOLDIETF-E | C5: ETF | D5: HOLD FULL | E5: {='📊 Portfolio Brief'!D11} -> 0.10932997 | F5: {=_xlfn.IFERROR(VLOOKUP(B5,'📥 Price Hub'!$B$5:$H$34,7,0),0)} -> 138.3 | G5: 84.4748 | H5: {='📊 Portfolio Brief'!J11} -> 0.63717464 | I5: {='📊 Portfolio Brief'!H11} -> 1106400 | J5: {='📊 Portfolio Brief'!I11} -> 430601.6 | K5: 8000 | L5: 0 | M5: Central bank demand, dollar re-rating, geopolitical hedge | N5: None — structural hold full position
B6: BAJFINANCE | C6: CONSUMER LENDING | D6: HOLD | E6: {='📊 Portfolio Brief'!D12} -> 0.070043215 | F6: {=_xlfn.IFERROR(VLOOKUP(B6,'📥 Price Hub'!$B$5:$H$34,7,0),0)} -> 945.1 | G6: 660 | H6: {='📊 Portfolio Brief'!J12} -> 0.4319697 | I6: {='📊 Portfolio Brief'!H12} -> 708825 | J6: {='📊 Portfolio Brief'!I12} -> 213825 | K6: 750 | L6: 0 | M6: Consumer lending market leader, 43% gain, strong franchise | N6: Quarterly earnings watch
B7: UJJIVANSFB | C7: MICROFINANCE | D7: HOLD — MONITOR | E7: {='📊 Portfolio Brief'!D13} -> 0.054024258 | F7: {=_xlfn.IFERROR(VLOOKUP(B7,'📥 Price Hub'!$B$5:$H$34,7,0),0)} -> 54.27 | G7: 41.8047 | H7: {='📊 Portfolio Brief'!J13} -> 0.29817939 | I7: {='📊 Portfolio Brief'!H13} -> 546715.98 | J7: {='📊 Portfolio Brief'!I13} -> 125575.43 | K7: 10074 | L7: 0 | M7: MFI stress cycle manageable; collection efficiency improving | N7: NPA trajectory + collection efficiency Q4
B8: COALINDIA | C8: METALS | D8: TRIM CANDIDATE | E8: {='📊 Portfolio Brief'!D14} -> 0.051599712 | F8: {=_xlfn.IFERROR(VLOOKUP(B8,'📥 Price Hub'!$B$5:$H$34,7,0),0)} -> 435.15 | G8: 388.9194 | H8: {='📊 Portfolio Brief'!J14} -> 0.11886936 | I8: {='📊 Portfolio Brief'!H14} -> 522180 | J8: {='📊 Portfolio Brief'!I14} -> 55476.72 | K8: 1200 | L8: 0 | M8: PSU dividend play — upside capped by govt pricing | N8: Trim on any rally; redeploy to conviction names
B9: ICICIBANK | C9: BANKING | D9: HOLD | E9: {='📊 Portfolio Brief'!D15} -> 0.050596236 | F9: {=_xlfn.IFERROR(VLOOKUP(B9,'📥 Price Hub'!$B$5:$H$34,7,0),0)} -> 1365.4 | G9: 1154.2536 | H9: {='📊 Portfolio Brief'!J15} -> 0.18292895 | I9: {='📊 Portfolio Brief'!H15} -> 512025 | J9: {='📊 Portfolio Brief'!I15} -> 79179.9 | K9: 375 | L9: 350 | M9: Best-in-class private bank, consistent compounder | N9: Hold through rate cycle
B10: HOMEFIRST | C10: HOUSING FINANCE | D10: HOLD | E10: {='📊 Portfolio Brief'!D16} -> 0.046820024 | F10: {=_xlfn.IFERROR(VLOOKUP(B10,'📥 Price Hub'!$B$5:$H$34,7,0),0)} -> 1074.4 | G10: 934.6512 | H10: {='📊 Portfolio Brief'!J16} -> 0.14951974 | I10: {='📊 Portfolio Brief'!H16} -> 473810.4 | J10: {='📊 Portfolio Brief'!I16} -> 61629.221 | K10: 441 | L10: 441 | M10: Affordable housing finance, all 441 shares LT | N10: Housing credit cycle watch
B11: CARYSIL | C11: FMCG | D11: HOLD | E11: {='📊 Portfolio Brief'!D17} -> 0.04669103 | F11: {=_xlfn.IFERROR(VLOOKUP(B11,'📥 Price Hub'!$B$5:$H$34,7,0),0)} -> 859.1 | G11: 743.8698 | H11: {='📊 Portfolio Brief'!J17} -> 0.15490641 | I11: {='📊 Portfolio Brief'!H17} -> 472505 | J11: {='📊 Portfolio Brief'!I17} -> 63376.61 | K11: 550 | L11: 425 | M11: Global quartz sink exporter, niche moat | N11: Export order momentum + US tariff impact
B12: BANKBARODA | C12: BANKING | D12: HOLD | E12: {='📊 Portfolio Brief'!D18} -> 0.04436342 | F12: {=_xlfn.IFERROR(VLOOKUP(B12,'📥 Price Hub'!$B$5:$H$34,7,0),0)} -> 299.3 | G12: 241.5191 | H12: {='📊 Portfolio Brief'!J18} -> 0.23923946 | I12: {='📊 Portfolio Brief'!H18} -> 448950 | J12: {='📊 Portfolio Brief'!I18} -> 86671.35 | K12: 1500 | L12: 0 | M12: PSU bank; sole PSU momentum play retained | N12: Monitor credit costs quarterly
B13: CREDITACC | C13: MICROFINANCE | D13: HOLD | E13: {='📊 Portfolio Brief'!D19} -> 0.042395007 | F13: {=_xlfn.IFERROR(VLOOKUP(B13,'📥 Price Hub'!$B$5:$H$34,7,0),0)} -> 1225.8 | G13: 961.5244 | H13: {='📊 Portfolio Brief'!J19} -> 0.27485064 | I13: {='📊 Portfolio Brief'!H19} -> 429030 | J13: {='📊 Portfolio Brief'!I19} -> 92496.46 | K13: 350 | L13: 275 | M13: Quality MFI, conservative underwriting, recovering | N13: MFI sector NPA trend Q4 FY26
B14: LT | C14: ENGINEERING & CAPITAL GOODS | D14: TRIM CANDIDATE | E14: {='📊 Portfolio Brief'!D20} -> 0.042202908 | F14: {=_xlfn.IFERROR(VLOOKUP(B14,'📥 Price Hub'!$B$5:$H$34,7,0),0)} -> 3882.6 | G14: 3614.1977 | H14: {='📊 Portfolio Brief'!J20} -> 0.074263314 | I14: {='📊 Portfolio Brief'!H20} -> 427086 | J14: {='📊 Portfolio Brief'!I20} -> 29524.253 | K14: 110 | L14: 0 | M14: Infra/engineering; +7% underwhelming for hold period | N14: Trim on rally; no LT shares, no friction
B15: NH | C15: HEALTHCARE | D15: HOLD | E15: {='📊 Portfolio Brief'!D21} -> 0.041360404 | F15: {=_xlfn.IFERROR(VLOOKUP(B15,'📥 Price Hub'!$B$5:$H$34,7,0),0)} -> 1744 | G15: 1336.4402 | H15: {='📊 Portfolio Brief'!J21} -> 0.30495925 | I15: {='📊 Portfolio Brief'!H21} -> 418560 | J15: {='📊 Portfolio Brief'!I21} -> 97814.352 | K15: 240 | L15: 200 | M15: Narayana healthcare compounder, Cayman asset-light inflecting | N15: Cayman revenue contribution H2 FY26+
B16: HDFCBANK | C16: BANKING | D16: HOLD | E16: {='📊 Portfolio Brief'!D22} -> 0.038626413 | F16: {=_xlfn.IFERROR(VLOOKUP(B16,'📥 Price Hub'!$B$5:$H$34,7,0),0)} -> 868.65 | G16: 626.6593 | H16: {='📊 Portfolio Brief'!J22} -> 0.38615991 | I16: {='📊 Portfolio Brief'!H22} -> 390892.5 | J16: {='📊 Portfolio Brief'!I22} -> 108895.82 | K16: 450 | L16: 175 | M16: Largest private bank, merger integration largely complete | N16: Credit growth + NIM recovery trajectory
... B31: SGB-COMBINED | C31: SOVEREIGN GOLD BOND | D31: HOLD TO MATURITY | E31: {='📊 Portfolio Brief'!D37} -> 0.0097192383 | F31: {=_xlfn.IFERROR(VLOOKUP(B31,'📥 Price Hub'!$B$5:$H$34,7,0),0)} -> 16392.83 | G31: 16262.96 | H31: {='📊 Portfolio Brief'!J37} -> 0 | I31: {='📊 Portfolio Brief'!H37} -> 98356.98 | J31: {='📊 Portfolio Brief'!I37} -> 779.22 | K31: 6 | L31: 0 | M31: 2 SGBs combined. Tax-free at maturity. | N31: Hold both to maturity — zero action
B34: TOTAL | H34: {=J34/SUM('📊 Portfolio Brief'!G11:G39)} -> 0.15128753 | I34: {=SUM(I5:I33)} -> 10119824 | J34: {=SUM(J5:J33)} -> 1329818.3

Sheet 📊 Portfolio Brief
B1: PORTFOLIO BRIEF — ALL HOLDINGS ANNOTATED
B2: BAJFINANCE avg corrected to ₹660 · Finance broken to sub-sectors · IT sector reviewed post AI-disruption analysis
B4: TOTAL INVESTED | E4: MARKET VALUE | H4: UNREALISED P&L | K4: RETURN | M4: # HOLDINGS
B5: {=G40} -> 8790005.6 | E5: ₹10,119,879 | H5: {=H40} -> 10119824 | K5: {=I40} -> 1329818.3 | M5: {=I40/G40} -> 0.15128753
B9: ALL HOLDINGS
B10: Symbol | C10: Sub-Sector | D10: Wt% | E10: Avg Cost | F10: CMP | G10: Invested (₹) | H10: Mkt Val (₹) | I10: P&L (₹) | J10: Ret % | K10: LT Qty | L10: Action | M10: Tag | N10: Notes
B11: GOLDIETF-E | C11: ETF | D11: {=H11/$H$40} -> 0.10932997 | E11: 84.4748 | F11: {=_xlfn.IFERROR(VLOOKUP(B11,'📥 Price Hub'!$B$5:$H$34,7,0),0)} -> 138.3 | G11: 675798.4 | H11: {=_xlfn.IFERROR(VLOOKUP(B11,'📥 Price Hub'!$B$5:$D$34,3,0)*F11,0)} -> 1106400 | I11: {=H11-G11} -> 430601.6 | J11: {=IF(G11=0,0,H11/G11-1)} -> 0.63717464 | K11: 0 | L11: HOLD FULL | M11: ⭐ CORE | N11: Structural hold. Central bank demand, dollar re-rating, geopolitical hedge intact. ~11% weight is intentional. No trim despite size — gold is in a structural demand scenario.
B12: BAJFINANCE | C12: CONSUMER LENDING | D12: {=H12/$H$40} -> 0.070043215 | E12: 660 | F12: {=_xlfn.IFERROR(VLOOKUP(B12,'📥 Price Hub'!$B$5:$H$34,7,0),0)} -> 945.1 | G12: 495000 | H12: {=_xlfn.IFERROR(VLOOKUP(B12,'📥 Price Hub'!$B$5:$D$34,3,0)*F12,0)} -> 708825 | I12: {=H12-G12} -> 213825 | J12: {=IF(G12=0,0,H12/G12-1)} -> 0.4319697 | K12: 0 | L12: HOLD | M12: ✅ RUNNING | N12: Avg corrected to ₹660. CMP ₹945 = ~43% gain. Consumer lending market leader, strong franchise.
B13: UJJIVANSFB | C13: MICROFINANCE | D13: {=H13/$H$40} -> 0.054024258 | E13: 41.8047 | F13: {=_xlfn.IFERROR(VLOOKUP(B13,'📥 Price Hub'!$B$5:$H$34,7,0),0)} -> 54.27 | G13: 421140.55 | H13: {=_xlfn.IFERROR(VLOOKUP(B13,'📥 Price Hub'!$B$5:$D$34,3,0)*F13,0)} -> 546715.98 | I13: {=H13-G13} -> 125575.43 | J13: {=IF(G13=0,0,H13/G13-1)} -> 0.29817939 | K13: 0 | L13: HOLD — MONITOR | M13: 👁 WATCH | N13: Ujjivan SFB. MFI stress cycle. Monitor NPA trajectory and collection efficiency quarterly.
B14: COALINDIA | C14: METALS | D14: {=H14/$H$40} -> 0.051599712 | E14: 388.9194 | F14: {=_xlfn.IFERROR(VLOOKUP(B14,'📥 Price Hub'!$B$5:$H$34,7,0),0)} -> 435.15 | G14: 466703.28 | H14: {=_xlfn.IFERROR(VLOOKUP(B14,'📥 Price Hub'!$B$5:$D$34,3,0)*F14,0)} -> 522180 | I14: {=H14-G14} -> 55476.72 | J14: {=IF(G14=0,0,H14/G14-1)} -> 0.11886936 | K14: 0 | L14: TRIM CANDIDATE | M14: ✂️ TRIM | N14: PSU with government-capped upside. Energy transition headwind even if decade away. No LT shares — clean trim available. Redeploy into conviction names.
B15: ICICIBANK | C15: BANKING | D15: {=H15/$H$40} -> 0.050596236 | E15: 1154.2536 | F15: {=_xlfn.IFERROR(VLOOKUP(B15,'📥 Price Hub'!$B$5:$H$34,7,0),0)} -> 1365.4 | G15: 432845.1 | H15: {=_xlfn.IFERROR(VLOOKUP(B15,'📥 Price Hub'!$B$5:$D$34,3,0)*F15,0)} -> 512025 | I15: {=H15-G15} -> 79179.9 | J15: {=IF(G15=0,0,H15/G15-1)} -> 0.18292895 | K15: 350 | L15: HOLD | M15: ✅ RUNNING | N15: Top-tier private bank. Consistent compounder. Core holding.
B16: HOMEFIRST | C16: HOUSING FINANCE | D16: {=H16/$H$40} -> 0.046820024 | E16: 934.6512 | F16: {=_xlfn.IFERROR(VLOOKUP(B16,'📥 Price Hub'!$B$5:$H$34,7,0),0)} -> 1074.4 | G16: 412181.18 | H16: {=_xlfn.IFERROR(VLOOKUP(B16,'📥 Price Hub'!$B$5:$D$34,3,0)*F16,0)} -> 473810.4 | I16: {=H16-G16} -> 61629.221 | J16: {=IF(G16=0,0,H16/G16-1)} -> 0.14951974 | K16: 441 | L16: HOLD | M16: ✅ RUNNING | N16: All 441 shares LT. Affordable housing finance. Full LTCG on any exit.
B17: CARYSIL | C17: FMCG | D17: {=H17/$H$40} -> 0.04669103 | E17: 743.8698 | F17: {=_xlfn.IFERROR(VLOOKUP(B17,'📥 Price Hub'!$B$5:$H$34,7,0),0)} -> 859.1 | G17: 409128.39 | H17: {=_xlfn.IFERROR(VLOOKUP(B17,'📥 Price Hub'!$B$5:$D$34,3,0)*F17,0)} -> 472505 | I17: {=H17-G17} -> 63376.61 | J17: {=IF(G17=0,0,H17/G17-1)} -> 0.15490641 | K17: 425 | L17: HOLD | M17: ✅ RUNNING | N17: Quartz kitchen sinks niche global exporter. 425/550 shares LT — LTCG friction on majority. Ongoing story.
B18: BANKBARODA | C18: BANKING | D18: {=H18/$H$40} -> 0.04436342 | E18: 241.5191 | F18: {=_xlfn.IFERROR(VLOOKUP(B18,'📥 Price Hub'!$B$5:$H$34,7,0),0)} -> 299.3 | G18: 362278.65 | H18: {=_xlfn.IFERROR(VLOOKUP(B18,'📥 Price Hub'!$B$5:$D$34,3,0)*F18,0)} -> 448950 | I18: {=H18-G18} -> 86671.35 | J18: {=IF(G18=0,0,H18/G18-1)} -> 0.23923946 | K18: 0 | L18: HOLD | M18: ✅ RUNNING | N18: PSU bank. +24% gain. Decent run. Lower conviction vs private banks but no exit reason.
B19: CREDITACC | C19: MICROFINANCE | D19: {=H19/$H$40} -> 0.042395007 | E19: 961.5244 | F19: {=_xlfn.IFERROR(VLOOKUP(B19,'📥 Price Hub'!$B$5:$H$34,7,0),0)} -> 1225.8 | G19: 336533.54 | H19: {=_xlfn.IFERROR(VLOOKUP(B19,'📥 Price Hub'!$B$5:$D$34,3,0)*F19,0)} -> 429030 | I19: {=H19-G19} -> 92496.46 | J19: {=IF(G19=0,0,H19/G19-1)} -> 0.27485064 | K19: 275 | L19: HOLD | M19: ✅ RUNNING | N19: CreditAccess Grameen. Quality MFI, conservative underwriting. 275/350 shares LT.
B20: LT | C20: ENGINEERING & CAPITAL GOODS | D20: {=H20/$H$40} -> 0.042202908 | E20: 3614.1977 | F20: {=_xlfn.IFERROR(VLOOKUP(B20,'📥 Price Hub'!$B$5:$H$34,7,0),0)} -> 3882.6 | G20: 397561.75 | H20: {=_xlfn.IFERROR(VLOOKUP(B20,'📥 Price Hub'!$B$5:$D$34,3,0)*F20,0)} -> 427086 | I20: {=H20-G20} -> 29524.253 | J20: {=IF(G20=0,0,H20/G20-1)} -> 0.074263314 | K20: 0 | L20: TRIM CANDIDATE | M20: ✂️ TRIM | N20: +7% for holding period is underwhelming for a large cap. No LT shares, no tax friction. Partial trim frees capital.
B21: NH | C21: HEALTHCARE | D21: {=H21/$H$40} -> 0.041360404 | E21: 1336.4402 | F21: {=_xlfn.IFERROR(VLOOKUP(B21,'📥 Price Hub'!$B$5:$H$34,7,0),0)} -> 1744 | G21: 320745.65 | H21: {=_xlfn.IFERROR(VLOOKUP(B21,'📥 Price Hub'!$B$5:$D$34,3,0)*F21,0)} -> 418560 | I21: {=H21-G21} -> 97814.352 | J21: {=IF(G21=0,0,H21/G21-1)} -> 0.30495925 | K21: 200 | L21: HOLD | M21: ⭐ CORE | N21: Narayana Hrudayalaya. 200/240 shares LT. Healthcare delivery compounder, asset-light model. Multi-year story.
B22: HDFCBANK | C22: BANKING | D22: {=H22/$H$40} -> 0.038626413 | E22: 626.6593 | F22: {=_xlfn.IFERROR(VLOOKUP(B22,'📥 Price Hub'!$B$5:$H$34,7,0),0)} -> 868.65 | G22: 281996.68 | H22: {=_xlfn.IFERROR(VLOOKUP(B22,'📥 Price Hub'!$B$5:$D$34,3,0)*F22,0)} -> 390892.5 | I22: {=H22-G22} -> 108895.82 | J22: {=IF(G22=0,0,H22/G22-1)} -> 0.38615991 | K22: 175 | L22: HOLD | M22: ✅ RUNNING | N22: Largest private bank. Merger integration largely complete. Core holding.
... B36: ECLERX | C36: SOFTWARE SERVICES | D36: {=H36/$H$40} -> 0.012735992 | E36: 3310.275 | F36: {=_xlfn.IFERROR(VLOOKUP(B36,'📥 Price Hub'!$B$5:$H$34,7,0),0)} -> 3222.15 | G36: 132411 | H36: {=_xlfn.IFERROR(VLOOKUP(B36,'📥 Price Hub'!$B$5:$D$34,3,0)*F36,0)} -> 128886 | I36: {=H36-G36} -> -3525 | J36: {=IF(G36=0,0,H36/G36-1)} -> -0.026621655 | K36: 0 | L36: HOLD — CONSIDER ADD | M36: 👁 CONSIDER ADD | N36: Domain-specialist KPO in capital markets analytics. NOT generic IT. Promoter at 54.5% bought back at ₹4,800 vs CMP ₹3,222 — the strongest possible signal. AI risk much lower than peers (domain judgment required). Consider modest add.
B37: SGB-COMBINED | C37: SOVEREIGN GOLD BOND | D37: {=H37/$H$40} -> 0.0097192383 | E37: 16262.96 | F37: {=_xlfn.IFERROR(VLOOKUP(B37,'📥 Price Hub'!$B$5:$H$34,7,0),0)} -> 16392.83 | G37: 97577.76 | H37: {=_xlfn.IFERROR(VLOOKUP(B37,'📥 Price Hub'!$B$5:$D$34,3,0)*F37,0)} -> 98356.98 | I37: {=H37-G37} -> 779.22 | J37: 0 | K37: HOLD TO MATURITY | L37: 🔒 MATURITY | M37: 🔒 MATURITY | N37: 2 SGBs: 4 units Dec-2031 + 2 units Apr-2028. Tax-free capital gains at maturity. Zero action.
B40: TOTAL | D40: 1 | G40: {=SUM(G11:G39)} -> 8790005.6 | H40: {=SUM(H11:H39)} -> 10119824 | I40: {=H40-G40} -> 1329818.3 | J40: {=I40/G40} -> 0.15128753

Sheet ⚡ Action Summary
B1: ACTION SUMMARY — WORKING CHECKLIST
B2: Numbers removed — live P&L/Wt% in 📡 LLM Context and 📊 Portfolio Brief. This sheet: actions + rationale only.
B4: 🎯 ACCUMULATE — BUILD POSITIONS
B5: Symbol | C5: Sub-Sector | H5: Action Note / Rationale
B6: UTKARSHBNK | C6: MICROFINANCE | H6: ACCUMULATE
B7: MEDIASSIST | C7: SOFTWARE SERVICES | H7: ACCUMULATE
B8: MEDIASSIST: target 6–7%, tranches now/May/ED closure. UTKARSHBNK: target 3–4%, turnaround confirmed by data. IEX: target 3–4%, accumulate ₹115–120; retain all 1,750 shares. See ⚡ IEX Deep Dive.
B10: ✂️ TRIM — FREE UP CAPITAL
B11: Symbol | C11: Sub-Sector | H11: Action Note / Rationale
B12: COALINDIA | C12: METALS | H12: TRIM CANDIDATE
B13: LT | C13: ENGINEERING & CAPITAL GOODS | H13: TRIM CANDIDATE
B15: CoalIndia + LT: partial trims for capital redeployment. Combined ~₹3–5L.
B17: 📈 TRIM ON STRENGTH
B18: Symbol | C18: Sub-Sector | H18: Action Note / Rationale
B19: SILVERCASE-E | C19: ETF | H19: TRIM ON STRENGTH
B20: Trim silver toward ₹30–32 on upmoves. Keep gold full.
B22: ⭐ CORE — DO NOTHING
B23: Symbol | C23: Sub-Sector | H23: Action Note / Rationale
B24: GOLDIETF-E | C24: ETF | H24: HOLD FULL
B25: NH | C25: HEALTHCARE | H25: HOLD
B26: CHAMBLFERT | C26: FERTILIZERS | H26: HOLD — WAIT
B27: EIDPARRY | C27: FMCG | H27: HOLD — PATIENT
B28: KIRLOSENG | C28: ENGINEERING & CAPITAL GOODS | H28: HOLD
B29: GOLDIETF: structural hold, no trim. CHAMBLFERT: wait for TAN revenue print. EIDPARRY: holdco patience trade.
B31: ✅ HOLD — RUNNING
B32: Symbol | C32: Sub-Sector | H32: Action Note / Rationale
B33: BAJFINANCE | C33: CONSUMER LENDING | H33: HOLD
B34: ICICIBANK | C34: BANKING | H34: HOLD
B35: HOMEFIRST | C35: HOUSING FINANCE | H35: HOLD
B36: CARYSIL | C36: FMCG | H36: HOLD
B37: BANKBARODA | C37: BANKING | H37: HOLD
B38: CREDITACC | C38: MICROFINANCE | H38: HOLD
B39: HDFCBANK | C39: BANKING | H39: HOLD
B40: FEDFINA | C40: HOUSING FINANCE | H40: HOLD
B41: Ongoing thesis, performing or recovering. Review quarterly.
B43: 👁 WATCH — DECISION PENDING
B44: Symbol | C44: Sub-Sector | H44: Action Note / Rationale
B45: UJJIVANSFB | C45: MICROFINANCE | H45: HOLD — MONITOR
B46: ASTRAMICRO | C46: DEFENCE | H46: WATCH — REVIEW
B47: CAMS | C47: MARKET INFRASTRUCTURE | H47: WATCH
B48: ZYDUSLIFE | C48: HEALTHCARE | H48: WATCH
B49: ASTRAMICRO: thesis delayed or broken? ZYDUSLIFE: small loss harvest option. CAMS: monitor for add opportunity.
B51: 🔍 IT CLUSTER — POST AI REVIEW
B52: Symbol | C52: Sub-Sector | H52: Action Note / Rationale
B53: PERSISTENT | C53: SOFTWARE SERVICES | H53: MONITOR RE-ENTRY
B54: ECLERX | C54: SOFTWARE SERVICES | H54: HOLD — CONSIDER ADD
B55: PERSISTENT: best Indian IT for AI era — sold at loss, consider re-entry. ECLERX: promoter buyback at ₹4,800 vs CMP ₹3,222 — consider modest add. See IT Deep Dive tab.
B57: 🔍 WATCHLIST — NOT YET HELD
B58: Symbol | C58: Sub-Sector | H58: Action Note / Rationale
B59: — See IT Deep Dive tab for detail —
B60: SAGILITY: US healthcare BPO, AI accelerates not disrupts, CMP ~₹50. Consider tracking position.
B62: 🔒 HOLD TO MATURITY
B63: Symbol | C63: Sub-Sector | H63: Action Note / Rationale
B64: SGB-COMBINED | C64: SOVEREIGN GOLD BOND | H64: HOLD TO MATURITY
B66: SGBs combined (6 units, 2 bonds). Tax-free at maturity. Zero action.

Sheet 🔬 Priority Research
B2: 🔬 PRIORITY RESEARCH — TOP 5 ACTIONS | Updated 6 March 2026
B3: Secondary reasoning and web research appended post-session. Source: Live web data, company filings, earnings calls.
B5: STOCK | C5: PRIORITY | D5: ACTION | E5: VERDICT | F5: RESEARCH NOTES — 6 Mar 2026
B7: ① MEDIASSIST — ACCUMULATE | Target 6–7%
B8: ED Risk Update | C8: ED search (April 4, 2025, Ranchi) is unchanged in status — management stated no adverse impact in Q3 FY26 filings. No escalation to formal charges or IRDAI action since the original search. This tail risk remains OPEN but has NOT worsened.
B9: ⚠️ NEW: GST Resolution | C9: Medi Assist TPA paid ₹4.83Cr to GST authorities (Feb 16–Mar 2, 2026 search) to avoid penalties. This is a POSITIVE development — the GST matter closed via payment rather than formal proceedings. Removes one uncertainty from the bear case.
B10: Q3 FY26 Results | C10: Consolidated revenue ₹2,396Cr (+64% YoY, Paramount consolidation driving bulk). Consolidated PAT ₹41Cr (down 86% YoY) — distorted by exceptional items: ₹37.68Cr cybersecurity costs, ₹33.27Cr labor codes, ₹71Cr advance pending reconciliation. STANDALONE PAT ₹118Cr (+222% YoY) — the clean business is doing well. 9M standalone PAT ₹374.92Cr. Company became debt-free from Jan 2026 confirmed.
B11: ⚠️ IRDAI Licence Renewal | C11: IRDAI TPA Licence (No. 003) validity: 20 March 2026 — expiry THIS MONTH. This is routine renewal but must be confirmed. If not renewed or delayed, it is an existential trigger. Track for confirmation by March 20.
B12: Integration Milestones | C12: Feb 6, 2026: Board approved Scheme of Merger — Paramount TPA (PHTPA) to be absorbed into MAITPA. Integration is proceeding structurally. Promoter reclassification from Promoter Group to Public filed Jan 2026 (SEBI Reg 31A) — not a red flag, routine corporate governance action.
B13: New Expansion | C13: Feb 27, 2026: Partnership with LawtonAsia to deploy AI health-insurance platform in Thailand. Implementation started, go-live expected soon. Small but signals the platform has export potential beyond India.
B14: 📌 Revised Action Note | C14: ACCUMULATE — thesis strengthened, not weakened. GST resolved. ED status quo (no escalation). IRDAI renewal this month is the single most important binary to track. Tranches: NOW (current ~₹340) → Q4 results May → ED closure. Add IRDAI renewal confirmation as Tranche 1 prerequisite watch. MIT underwater at ₹535 remains anchor.
B16: ② CHAMBLFERT — HOLD / WAIT | TAN April 2026
B17: TAN Status — CONFIRMED | C17: Q3 FY26 earnings call (Feb 13, 2026): Management REAFFIRMED April 30, 2026 commissioning. No further slippage. Engineering 99.86% done, procurement 99.80%, construction 88.01%. Total completion 92.65%. ₹1,184Cr spent of ₹1,645Cr. Catalyst is ON SCHEDULE and approaching fast.
B18: Q3 FY26 Financials | C18: Standalone revenue ₹5,898Cr (+20% YoY), EBITDA ₹821Cr (+6%), PAT ₹565Cr (+12%). 9M revenue +27%, PAT +16%. Base business performing well. CPC & Specialty Nutrients +33% YoY. Complex fertilisers +81% YoY. Biologicals growing.
B19: ⚠️ Margin Compression | C19: EBITDA margin Q3: 13.92% vs 15.82% prior year (–190bps). 9M: 13.46% vs 16.34% prior year. Driven by input cost pressure (sulfur, phosphoric acid, ammonia). Not alarming — base urea margins have ceiling (NIP-2012). The TAN business (no subsidy, no margin cap) is the structural fix. Monitor but within acceptable range.
B20: Gadepan-II Shutdown | C20: Planned maintenance shutdown for Gadepan-II plant: Feb 20, 2026, ~30-35 days. This will create a small Q4 volume dip for urea — already flagged by management. Non-event, scheduled maintenance. Watch Q4 FY26 results for confirmation.
B21: Future Growth Signals | C21: ICRA reaffirmed TAN commercial operations April 2026. NIP-2012 policy (G-3 plant) expires Dec 2026 — policy uncertainty risk on urea returns, but TAN addresses this by reducing subsidy dependence. IMACID JV capacity expanding from 5 to 7 lakh MT P2O5 by Dec 2026. Management exploring vertical and horizontal TAN expansion (LDAN capacity already provisioned in plant design). Agreement with TERI for advanced agricultural solutions.
B22: 📌 Revised Action Note | C22: HOLD — DO NOTHING. TAN catalyst is on track and imminent. Conviction HIGH. Watch for: (a) any April delay announcements, (b) first TAN revenue in Q1/Q2 FY27 results. The ₹654 peak hit in Apr 2025 on TAN expectations is likely to revisit once first revenue prints. Hold full 850 shares.
B24: ③ UTKARSHBNK — ACCUMULATE | Target 3–4%
B25: Q3 FY26 — Net Loss ₹375Cr | C25: Net loss ₹375Cr for Q3; 9M loss ₹963Cr. This is KNOWN stress — fully provisioned. The loss is the price of front-loading provisions. Pre-provision operating loss only ₹44Cr (small). Loan portfolio contracted 3.9% YoY to ₹18,306Cr — intentional, not distress.
B26: ✅ DPD Inflection Confirmed | C26: JLG 1-to-90 DPD: ₹378Cr (Oct 2025) → <₹50Cr (Jan 2026). 87% reduction in 3 months. 1-to-30 DPD (freshest stress): ₹170Cr → <₹50Cr. These numbers are REAL and non-reversible for the cohort already cleared. The October 2025 festival season was the absolute stress peak.
B27: ✅ Disbursements Recovering | C27: Monthly disbursements: ₹800Cr (Oct) → ₹1,000Cr (Nov) → ₹1,100Cr (Dec) → ₹1,200Cr+ (Jan 2026). 50% growth in 3 months. Critically: JLG segment itself started growing again from January — first time in multiple quarters.
B28: Collection Efficiency | C28: X-bucket efficiency: 99.1% overall Q3; 99.5% JLG-specific in December. January even higher. Management guidance: will not fall below 99.5% again. CAR 20.1% (post ₹950Cr rights). LCR 207%, surplus liquidity ₹4,700Cr. This bank is not a capital risk.
B29: Asset Mix Transformation | C29: Secured lending: 50% of loan book (from 41% a year ago, 10% in early years). JLG exposure down from 90% (FY20) to 33% now. This bank structurally CANNOT repeat the same MFI stress — the business model is changing. Deposits +4.5% YoY despite stress; retail term deposits +23.8% YoY; CASA ratio improved to 21.9%.
B30: ⚠️ Management Changes | C30: CHRO Hitain Sharma resigned Feb 27, 2026. Director Muralidharan Rajamani ceased Mar 2, 2026 (5-year term completion — routine). Worth monitoring for further senior exits, but no red flag yet. Smart money (FIIs +10.12%, DIIs +7.35%) accumulated in Q3 — the same quarter of worst-ever quarterly loss.
B31: 📌 Revised Action Note | C31: ACCUMULATE — conviction STRONGER. Q4 FY26 is expected to be first visible QoQ AUM growth on pre-write-off basis (catalyst: next quarterly result ~May 2026). Add in tranches each quarter clean data prints. Current weight ~2.9%. Target 3–4%. Gross NPA still at 11% — this is the legacy tail, not new slippages. Monitor: monthly collection data, Q4 JLG NPA formation.
B33: ④ ASTRAMICRO — THESIS DELAYED, NOT BROKEN | Hold, do NOT harvest
B34: Q3 FY26 — Sequential Recovery | C34: Standalone revenue ₹258Cr (+0.66% YoY, but +21.28% QoQ). Q2 was the trough. EBITDA ₹80Cr, margin 30.9% standalone / 31.7% consolidated — BEST margin in many quarters. PAT ₹39Cr standalone, ₹47Cr consolidated. 9M FY26: highest-ever nine-month performance across revenue, EBITDA and PAT.
B35: ✅ Order Book at Record ₹2,226Cr | C35: Standalone order book ₹2,226Cr as of Dec 31, 2025 (2x annual revenue — strong visibility). Consolidated ₹2,566Cr. Q3 new orders: ₹476Cr. 9M order inflows: ₹852Cr. Q4 FY26 guidance: ₹550–600Cr of new orders (radar + EW systems). FY27 guidance: ₹1,500–1,600Cr.
B36: ✅ NEW: Demerger Approved | C36: Feb 27, 2026: Board gave in-principle approval for DEMERGER of Space, Meteorology & Hydrology businesses into a separate entity. This is a VALUE UNLOCK catalyst NOT in the original thesis. Focused entities, separate growth strategies, potential re-rating. Astra Space Technologies (wholly-owned sub, ex-CFO moved there) is the vehicle. This changes the calculus against tax-loss harvesting.
B37: Why Flat Revenue | C37: Revenue flat YoY (0.66%) because defence projects have long gestation — approvals, inspections, delivery schedules delayed by government processes, NOT business failure. High receivables and inventory are inherent to long-gestation contracts. Customer advances 20-30% mitigate exposure. This is a structural feature of the business, not deterioration.
B38: Strategic Catalysts | C38: MoU with BEL for indigenous design and production in key defence technologies — opens production order pipeline with India's largest defence PSU. Astra Rafael Comsys JV: $18.19M executed in Q3, $80M order book, ₹350Cr+ FY26 revenue, ₹400Cr+ FY27. PBT margins 10-12%. AMCA (fighter jet) program: Astra targeted as radar and EW suite supplier. Defence budget FY26: ₹7.85 lakh Cr (record).
B39: 📌 Revised Action Note | C39: VERDICT: THESIS DELAYED, NOT BROKEN. Do NOT tax-loss harvest. Q3 showed sequential recovery (margins, revenue). Order book at record. Demerger is a new unlocking catalyst. Key ask: need to see FY27 order inflows confirm ₹1,500Cr guidance (watch Q4 and Q1 FY27 results). If confirmed, this becomes a CORE position. Exit trigger stays: order book degrading below ₹1,500Cr, AMCA program removed.
B41: ⑤ IEX — ACCUMULATE | Build to 3–4% target weight. Zones: ₹115–120 (strong), ₹100–105 (aggressive add)
B42: ⚠️ APTEL Ruling — Feb 13 | C42: APTEL disposed IEX's appeal on Feb 13, 2026. CERC can now proceed with market coupling framework. HOWEVER: APTEL explicitly stated market coupling CANNOT be implemented until CERC notifies specific formal regulations. As of the ruling date, not even draft regulations had been issued. This means implementation is deferred — not dead.
B43: Coupling Timeline — Pushed | C43: JM Financial estimates coupling not before December 2027. CERC's own corrigendum reclassified its July 2025 'order' as 'directions' — reducing legal force. The regulatory pathway now requires: draft regulations → public comments → final regulations → implementation. Multi-step process means 18–24 month runway minimum.
B44: SEBI Insider Trading | C44: SEBI's Oct 2025 interim order found prima facie insider trading by CERC officials and connected entities trading in IEX options ahead of the July 23 coupling announcement. This taints the CERC order's credibility and is a legal anchor for IEX in any future challenge to final regulations. The regulator's credibility is damaged — helps IEX's long-term fight.
B45: ✅ Business Performing | C45: Feb 2026 volume: 12,550 MU — 30.4% YoY growth. Highest daily average volume ever. Business fundamentals are strong and accelerating. Electricity demand is structural. This is purely a regulatory overhang trade, not a deteriorating business story.
B46: Analyst Sentiment | C46: Bloomberg consensus: 4 Buy, 3 Hold, 6 Sell. Average 12-month target implies ~1% downside from current levels. Market is split. The Bear case: coupling erodes pricing power over 3–5 years. Bull case: coupling delayed to 2027+, volumes accelerate, overhang lifts. IEX has liberty to challenge final regulations when notified.
B47: 📌 Revised Action Note | C47: ACCUMULATING — position being increased. Market wrong on timing + magnitude. Coupling min 18–24 months away. Volume +30% YoY. Tainted CERC reduces enforcement appetite. Dividend yield ~2.5% while waiting. Target 3–4% weight. See ⚡ IEX Deep Dive for full thesis + triggers.
B49: Research conducted 6 March 2026 · Sources: Company filings, BSE/NSE announcements, Q3 FY26 earnings calls, SEBI/APTEL orders, live web data · For decision support only — not investment advice
B52: ⑥ ZYDUSLIFE — EXIT VALIDATED | Good quarter, wrong portfolio slot
B53: Q3 FY26 — Actually Strong | C53: Research confirms: Q3 FY26 revenue +30% YoY to ₹6,864Cr. EBITDA +31% to ₹1,816Cr. Margin 26.5% (+20bps). Adjusted PAT +9% to ₹1,110Cr. US generics growing 16% YoY. India branded formulations +14% YoY. Pipeline milestones: Andy robotic system CE mark, Saroglitazar NDA filing imminent, Zycubo FDA approval (Menkes disease — first-ever therapy). 9M EBITDA margin 30.3% (+80bps). The business is performing well. This is important context for the exit logic.
B54: Why EXIT Anyway — The capital opportunity cost case | C54: The exit is NOT because Zydus is failing. It is because: 1. NO EDGE THESIS: Original file noted 'thesis clarity needed.' Research confirms this. Zydus is a diversified pharma — good execution but nothing in the portfolio creates an information edge vs the consensus. You are holding a well-run large-cap that anyone can own. 2. NO LT SHARES: 100% STCL harvest (–3.4%, ~₹9,400). You exit on a strong quarter — stock is up on results, giving a better execution price. 3. OPPORTUNITY COST: That ₹2.7L does 10x more work in MEDIASSIST (where you have a thesis edge: MIT anchor, TPA platform moat, Paramount integration) or NH (Cayman inflecting, cheapest hospital chain). Both have a specific reason only YOU have surfaced vs Zydus which is fully consensus. 4. DEBT ADDED: Net debt went from zero (FY25) to ₹2,872Cr (Dec 2025) due to acquisitions (Amplitude Surgical, Comfort Click, Agenus CDMO). +0.36x debt/EBITDA is still low but was a clean balance sheet — integration risk now present. 5. SEQUENTIAL RISK: Q2 FY26 showed sequential PAT decline of 17.2%. Q3 recovered but the lumpiness is real. Specialty products (Lenalidomide-type) have cliff risk.
B55: Exit Mechanics | C55: Timing: Exit this week while Q3 results are fresh and stock trades ~₹897–920. Avoid waiting for it to give back gains. Tax: STCL ~₹9,400 (300 shares × ~₹31 loss per share at avg ₹928). Minor but useful against future STCG on BANKBARODA trim or COALINDIA trim. Proceeds: ~₹2.7L → primary allocation to MEDIASSIST (post IRDAI confirmation Mar 20), secondary to NH top-up. 📌 VERDICT: Exit confirmed. Not because Zydus is broken — it isn't. Because ₹2.7L works harder elsewhere in a more differentiated thesis.

Sheet 🗺️ Portfolio Roadmap
B1: 🗺️ PORTFOLIO ROADMAP — 29 → 25 → 20 | Revised 7 Mar 2026 | Merges: Road to 20 + Consolidation Plan
B2: 27 active holdings (LIQUIDBEES removed, SGBs combined) · Wave 1 = execute this week · Wave 2 = gradual over 6-9 months
B4: 🚪 WAVE 1 EXITS — 29 → 26 | Execute this week | 3 confirmed exits
B5: STOCK | C5: WT | D5: P&L | E5: TAX | F5: PROCEEDS | G5: DEPLOY INTO | H5: RATIONALE
B6: ZYDUSLIFE | C6: 2.7% | D6: −3.4% | E6: STCL ~₹9,400 | F6: ~₹2.7L | G6: NH top-up | H6: No edge thesis. Exit on good quarter. Loss harvest useful offset.
B7: RAINBOW | C7: 2.8% | D7: −5% | E7: LTCL harvest (zero LTCG) | F7: ~₹2.85L | G7: NH top-up | H7: Duplicate vs NH. Occupancy 47% vs target 55-60%. NH stronger compounder.
B8: LT | C8: 4.2% | D8: +7% | E8: STCG ~₹2,100 (minimal) | F8: ~₹4.3L | G8: MEDIASSIST primary | H8: Underwhelming return. KIRLOSENG covers capex. No LT friction. Deploy to conviction.
B10: ✂️ WAVE 1 TRIMS — Concurrent with exits
B11: STOCK | C11: CUR WT | D11: TARGET WT | E11: SHARES TO SELL | F11: PROCEEDS | G11: TAX NOTE | H11: REDEPLOY INTO
B12: UJJIVANSFB | C12: 5.4% | D12: 2.5–3% | E12: ~5,000 shares | F12: ~₹2.7L | G12: STCG on +30% ~₹37,500 | H12: UTKARSHBNK primary · CREDITACC on dips
B13: COALINDIA | C13: 5.2% | D13: 2.5–3% | E13: ~420 shares | F13: ~₹1.8L | G13: STCG on +12% ~₹6,600 | H13: NH top-up
B15: ⚡ EXECUTION SEQUENCE — Ordered by urgency
B16: STEP | C16: TIMING | D16: ACTION | E16: STOCK | F16: CAPITAL IMPACT | G16: NOTE
B17: 1 | C17: NOW | D17: ACCUMULATE | E17: IEX | F17: ₹115–120 zone | G17: Build to 3-4%. See ⚡ IEX Deep Dive
B18: 2 | C18: BEFORE MAR 20 | D18: MONITOR — do NOT add yet | E18: MEDIASSIST | F18: Watch IRDAI renewal | G18: Binary — confirm licence renewal Mar 20 before adding
B19: 3 | C19: THIS WEEK | D19: EXIT all 300 shares | E19: ZYDUSLIFE | F19: ~₹2.7L freed | G19: STCL ~₹9,400 — useful offset
B20: 4 | C20: THIS WEEK | D20: EXIT all 235 shares | E20: RAINBOW | F20: ~₹2.85L freed | G20: LTCL + STCL harvest. Zero LTCG
B21: 5 | C21: THIS WEEK | D21: TRIM ~420 shares | E21: COALINDIA | F21: ~₹1.8L freed | G21: STCG ~₹6,600 on +12%
B22: 6 | C22: THIS WEEK | D22: TRIM ~5,000 shares | E22: UJJIVANSFB | F22: ~₹2.7L freed | G22: STCG ~₹37,500 on +30%
B23: 7 | C23: THIS WEEK / AFTER IRDAI | D23: EXIT all 110 shares (keep 20 tracker if wanted) | E23: LT | F23: ~₹4.3L freed | G23: STCG ~₹2,100 — minimal
B24: 8 | C24: AFTER EXITS | D24: ADD ~100–120 shares | E24: NH | F24: Deploy RAINBOW + COALINDIA ~₹5L | G24: Fresh STCG basis
B25: 9 | C25: AFTER IRDAI MAR 20 | D25: ADD tranches | E25: MEDIASSIST | F25: Deploy LT proceeds ~₹3–4L | G25: Fresh basis at ~₹340
B26: 10 | C26: EACH CLEAN QUARTER | D26: ADD tranches | E26: UTKARSHBNK | F26: Deploy UJJIVANSFB proceeds ~₹2L+ | G26: Fresh basis at ~₹13
B27: 11 | C27: ON DIPS | D27: ADD opportunistically | E27: CREDITACC | F27: Residual trim proceeds | G27: 275 LT already held
B28: 12 | C28: ON DIPS | D28: MODEST ADD ~10–15 shares | E28: ECLERX | F28: ~₹0.3–0.5L | G28: Promoter ₹4,800 signal anchor
B30: 💰 CAPITAL REDEPLOYMENT — ~₹11–12L freed → where it goes
B31: TARGET | C31: SECTOR | D31: CAPITAL FROM | E31: AMOUNT | F31: NEW WT | G31: NOTE
B32: NH | C32: HEALTHCARE | D32: RAINBOW + partial COALINDIA | E32: ~₹4–5L | F32: 6–7% | G32: Cayman inflecting. Cheapest hospital chain. 200 LT held, add 100-120 more.
B33: UTKARSHBNK | C33: MICROFINANCE | D33: UJJIVANSFB trim (primary) | E33: ~₹2L+ | F33: 4–5% | G33: DPD 87% cleared. Smart money rights ₹14. Add each clean quarterly print.
B34: MEDIASSIST | C34: HEALTHCARE INFRA | D34: LT exit + partial ZYDUS | E34: ~₹3–4L | F34: 5–6% | G34: Post IRDAI confirmation Mar 20. MIT anchor ₹535 vs CMP ₹340.
B35: CREDITACC | C35: MICROFINANCE | D35: UJJIVANSFB trim (secondary — dips only) | E35: ~₹0.7L | F35: 4.5–5% | G35: 275 LT held. Quality MFI anchor. Opportunistic only.
B37: 🎯 TARGET PORTFOLIO — 25 stocks now → 20 stocks (6-9 months)
B38: # | C38: STOCK | D38: SECTOR | E38: ACTION | F38: TARGET WT | G38: CONVICTION | H38: THESIS IN ONE LINE
B39: 1 | C39: GOLDIETF-E | D39: ETF / GOLD | E39: HOLD FULL | F39: 10–11% | G39: ⭐ STRUCTURAL | H39: Central bank demand + dollar re-rating. No trim.
B40: 2 | C40: BAJFINANCE | D40: CONSUMER LENDING | E40: HOLD | F40: 6–7% | G40: ⭐ CORE | H40: Consumer lending market leader. 43% gain. Running.
B41: 3 | C41: NH | D41: HEALTHCARE | E41: SIZE UP → HOLD | F41: 6–7% | G41: ⭐ HIGH CONV. | H41: Cayman inflecting. Cheapest hospital chain. Asset-light compounder.
B42: 4 | C42: MEDIASSIST | D42: HEALTHCARE INFRA | E42: ACCUMULATE | F42: 5–7% | G42: ⭐ HIGH CONV. | H42: TPA market leader. MIT anchor ₹535. Platform moat.
B43: 5 | C43: ICICIBANK | D43: BANKING | E43: HOLD | F43: 5–6% | G43: ⭐ CORE | H43: Best-in-class private bank. Consistent compounder.
B44: 6 | C44: HOMEFIRST | D44: HOUSING FINANCE | E44: HOLD | F44: 4–5% | G44: ⭐ CORE | H44: 441 LT shares. Affordable housing cycle.
B45: 7 | C45: CARYSIL | D45: FMCG / EXPORT | E45: HOLD | F45: 4–5% | G45: HIGH | H45: Niche quartz sink exporter. 425 LT. Global cycle play.
B46: 8 | C46: BANKBARODA | D46: PSU BANKING | E46: HOLD (MOMENTUM) | F46: 4–5% | G46: HIGH | H46: Sole PSU exposure. Momentum trade. Not consensus.
B47: 9 | C47: CREDITACC | D47: MICROFINANCE | E47: HOLD + ADD DIPS | F47: 4–5% | G47: HIGH | H47: 275 LT. Conservative MFI underwriting. Quality anchor.
B48: 10 | C48: CHAMBLFERT | D48: FERTILIZERS / TAN | E48: HOLD — WAIT | F48: 4–5% | G48: ⭐ HIGH CONV. | H48: TAN commissioning April 2026. First revenue Q1/Q2 FY27.
B49: 11 | C49: HDFCBANK | D49: BANKING | E49: HOLD | F49: 4% | G49: ⭐ CORE | H49: 175 LT. Merger integration done. Core holding.
B50: 12 | C50: ASTRAMICRO | D50: DEFENCE | E50: HOLD — UPGRADED | F50: 4–5% | G50: HIGH | H50: Demerger catalyst. Order book ₹2,226Cr record.
... B58: 20 | C58: SGB-COMBINED | D58: SOVEREIGN GOLD | E58: HOLD TO MATURITY | F58: 1.0% | G58: LOCKED | H58: 2 SGBs combined. Tax-free at maturity. Zero action.
B60: 🌊 WAVE 2 EXITS — 25 → 20 | Gradual over 6-9 months | Not urgent sells
B61: STOCK | C61: WT | D61: P&L | E61: TIMING | F61: RATIONALE
B62: SILVERCASE-E | C62: 1.3% | D62: +18.7% | E62: Trim now, exit on strength ₹30-32 | F62: Silver at 1.3% too small. No structural thesis. Exit cleanly → GOLDIETF + SGBs cover precious metals.
B63: FEDFINA | C63: 2.0% | D63: +15% | E63: 3–6 months on portfolio strength | F63: 1,450 LT at +15%. Small trapped position. Gold loan angle = GOLDIETF. Better use in MEDIASSIST or NH.
B64: CAMS | C64: 2.8% | D64: −10.7% | E64: 6–12 months, watch MF AUM | F64: Record revenue. Passive India AUM beneficiary. No LLM edge vs consensus. If falls to ₹550–570: add or exit. Do not drift.
B65: UJJIVANSFB | C65: 5.4% → 3% | D65: +30% | E65: Wave 1 trim already planned | F65: After trim to 3%, reassess. Full exit in Wave 2 if UTKARSHBNK absorbs the MFI thesis cleanly.
B67: Revised 7 Mar 2026 · Tax notes indicative — verify with CA · STCG 20% · LTCG 12.5% above ₹1.25L exemption · Replaces: 🎯 Road to 20 + 🔀 Consolidation Plan

Sheet ⚠️ Risk Flags
B1: RISK & CONCENTRATION FLAGS
B3: Symbol | C3: Sector | D3: Flag Type | E3: Detail | F3: Severity
B4: GOLDIETF-E | C4: ETF | D4: CONCENTRATION | E4: Single stock 10.9% of portfolio (>10%) | F4: HIGH
B5: GOLDIETF-E | C5: ETF | D5: LARGE GAIN — REVIEW | E5: Gain +63.7% — LTCG & rebalancing? | F5: NOTE
B6: CHAMBLFERT | C6: FERTILIZERS | D6: MODERATE LOSS | E6: Unrealised loss -8.7% | F6: MEDIUM
B7: UTKARSHBNK | C7: MICROFINANCE | D7: MODERATE LOSS | E7: Unrealised loss -6.4% | F7: MEDIUM
B8: CAMS | C8: MARKET INFRASTRUCTURE | D8: MODERATE LOSS | E8: Unrealised loss -10.7% | F8: MEDIUM
B9: MEDIASSIST | C9: SOFTWARE SERVICES | D9: DEEP LOSS | E9: Unrealised loss -18.2% — review thesis | F9: HIGH
B10: IEX | C10: ENERGY | D10: DEEP LOSS — THESIS INTACT | E10: Unrealised loss -18.2% — thesis confirmed, accumulating. Coupling 18–24 months away. Volume +30% YoY. Tainted CERC = reduced enforcement risk. | F10: MEDIUM
B11: PERSISTENT | C11: SOFTWARE SERVICES | D11: MODERATE LOSS | E11: Unrealised loss -8.4% | F11: MEDIUM
B12: PORTFOLIO | C12: FINANCE (ALL SUBS) | D12: AGGREGATE FINANCE EXPOSURE | E12: All finance sub-sectors combined = 42.3% of portfolio | F12: NOTE
B15: Analysis as of 5 Mar 2026 | 9 flags | 29 holdings | BAJFINANCE avg corrected to ₹660

Sheet 🎯 Scenario Analysis
B1: SCENARIO ANALYSIS
B2: Uniform market move on CMP. LTCG at 12.5% on LT gains >₹1.25L exemption. Estimates only.
B4: Scenario | C4: Move | D4: Portfolio Value (₹) | E4: Total P&L (₹) | F4: Return on Cost | G4: Change vs Today (₹) | H4: Est. LTCG Tax (₹) | I4: Post-Tax Value (₹)
B5: Bear (−20%) | C5: -20% | D5: {=SUM(H14:H42)} -> 8095859.1 | E5: {=D5-'📊 Portfolio Brief'!$G$40} -> -694146.51 | F5: {=E5/'📊 Portfolio Brief'!$G$40} -> -0.078969973 | G5: {=D5-D7} -> -2023964.8 | H5: 0 | I5: 8095903.1
B6: Mild Bear (−10%) | C6: -10% | D6: {=SUM(I14:I42)} -> 9107841.5 | E6: {=D6-'📊 Portfolio Brief'!$G$40} -> 317835.88 | F6: {=E6/'📊 Portfolio Brief'!$G$40} -> 0.03615878 | G6: {=D6-D7} -> -1011982.4 | H6: 12945.887 | I6: 9094945.1
B7: Base (0% — Today) | C7: +0% | D7: {=SUM(J14:J42)} -> 10119824 | E7: {=D7-'📊 Portfolio Brief'!$G$40} -> 1329818.3 | F7: {=E7/'📊 Portfolio Brief'!$G$40} -> 0.15128753 | G7: {=D7-D7} -> 0 | H7: 45361.464 | I7: 10074517
B8: Bull (+15%) | C8: +15% | D8: {=SUM(K14:K42)} -> 11637797 | E8: {=D8-'📊 Portfolio Brief'!$G$40} -> 2847791.8 | F8: {=E8/'📊 Portfolio Brief'!$G$40} -> 0.32398066 | G8: {=D8-D7} -> 1517973.6 | H8: 100286.63 | I8: 11537574
B9: Strong Bull (+30%) | C9: +30% | D9: {=SUM(L14:L42)} -> 13155771 | E9: {=D9-'📊 Portfolio Brief'!$G$40} -> 4365765.4 | F9: {=E9/'📊 Portfolio Brief'!$G$40} -> 0.49667379 | G9: {=D9-D7} -> 3035947.2 | H9: 160097.54 | I9: 12995745
B12: STOCK-LEVEL SCENARIO VALUES
B13: Symbol | C13: Sector | D13: Qty | E13: Avg Cost | F13: CMP | G13: Today Val | H13: Bear −20% | I13: Mild −10% | J13: Base 0% | K13: Bull +15% | L13: S.Bull +30% | M13: Bear P&L | N13: Base P&L | O13: Bull P&L | P13: S.Bull P&L
B14: GOLDIETF-E | C14: ETF | D14: 8000 | E14: 84.4748 | F14: {=_xlfn.IFERROR(VLOOKUP(B14,'📥 Price Hub'!$B$5:$H$34,7,0),0)} -> 138.3 | G14: {=D14*F14} -> 1106400 | H14: {=G14*0.8} -> 885120 | I14: {=G14*0.9} -> 995760 | J14: {=G14} -> 1106400 | K14: {=G14*1.15} -> 1272360 | L14: {=G14*1.3} -> 1438320 | M14: {=H14-E14*D14} -> 209321.6 | N14: {=J14-E14*D14} -> 430601.6 | O14: {=K14-E14*D14} -> 596561.6 | P14: {=L14-E14*D14} -> 762521.6
B15: BAJFINANCE | C15: CONSUMER LENDING | D15: 750 | E15: 660 | F15: {=_xlfn.IFERROR(VLOOKUP(B15,'📥 Price Hub'!$B$5:$H$34,7,0),0)} -> 945.1 | G15: {=D15*F15} -> 708825 | H15: {=G15*0.8} -> 567060 | I15: {=G15*0.9} -> 637942.5 | J15: {=G15} -> 708825 | K15: {=G15*1.15} -> 815148.75 | L15: {=G15*1.3} -> 921472.5 | M15: {=H15-E15*D15} -> 72060 | N15: {=J15-E15*D15} -> 213825 | O15: {=K15-E15*D15} -> 320148.75 | P15: {=L15-E15*D15} -> 426472.5
B16: UJJIVANSFB | C16: MICROFINANCE | D16: 10074 | E16: 41.8047 | F16: {=_xlfn.IFERROR(VLOOKUP(B16,'📥 Price Hub'!$B$5:$H$34,7,0),0)} -> 54.27 | G16: {=D16*F16} -> 546715.98 | H16: {=G16*0.8} -> 437372.78 | I16: {=G16*0.9} -> 492044.38 | J16: {=G16} -> 546715.98 | K16: {=G16*1.15} -> 628723.38 | L16: {=G16*1.3} -> 710730.77 | M16: {=H16-E16*D16} -> 16232.236 | N16: {=J16-E16*D16} -> 125575.43 | O16: {=K16-E16*D16} -> 207582.83 | P16: {=L16-E16*D16} -> 289590.23
B17: COALINDIA | C17: METALS | D17: 1200 | E17: 388.9194 | F17: {=_xlfn.IFERROR(VLOOKUP(B17,'📥 Price Hub'!$B$5:$H$34,7,0),0)} -> 435.15 | G17: {=D17*F17} -> 522180 | H17: {=G17*0.8} -> 417744 | I17: {=G17*0.9} -> 469962 | J17: {=G17} -> 522180 | K17: {=G17*1.15} -> 600507 | L17: {=G17*1.3} -> 678834 | M17: {=H17-E17*D17} -> -48959.28 | N17: {=J17-E17*D17} -> 55476.72 | O17: {=K17-E17*D17} -> 133803.72 | P17: {=L17-E17*D17} -> 212130.72
B18: ICICIBANK | C18: BANKING | D18: 375 | E18: 1154.2536 | F18: {=_xlfn.IFERROR(VLOOKUP(B18,'📥 Price Hub'!$B$5:$H$34,7,0),0)} -> 1365.4 | G18: {=D18*F18} -> 512025 | H18: {=G18*0.8} -> 409620 | I18: {=G18*0.9} -> 460822.5 | J18: {=G18} -> 512025 | K18: {=G18*1.15} -> 588828.75 | L18: {=G18*1.3} -> 665632.5 | M18: {=H18-E18*D18} -> -23225.1 | N18: {=J18-E18*D18} -> 79179.9 | O18: {=K18-E18*D18} -> 155983.65 | P18: {=L18-E18*D18} -> 232787.4
B19: HOMEFIRST | C19: HOUSING FINANCE | D19: 441 | E19: 934.6512 | F19: {=_xlfn.IFERROR(VLOOKUP(B19,'📥 Price Hub'!$B$5:$H$34,7,0),0)} -> 1074.4 | G19: {=D19*F19} -> 473810.4 | H19: {=G19*0.8} -> 379048.32 | I19: {=G19*0.9} -> 426429.36 | J19: {=G19} -> 473810.4 | K19: {=G19*1.15} -> 544881.96 | L19: {=G19*1.3} -> 615953.52 | M19: {=H19-E19*D19} -> -33132.859 | N19: {=J19-E19*D19} -> 61629.221 | O19: {=K19-E19*D19} -> 132700.78 | P19: {=L19-E19*D19} -> 203772.34
B20: CARYSIL | C20: FMCG | D20: 550 | E20: 743.8698 | F20: {=_xlfn.IFERROR(VLOOKUP(B20,'📥 Price Hub'!$B$5:$H$34,7,0),0)} -> 859.1 | G20: {=D20*F20} -> 472505 | H20: {=G20*0.8} -> 378004 | I20: {=G20*0.9} -> 425254.5 | J20: {=G20} -> 472505 | K20: {=G20*1.15} -> 543380.75 | L20: {=G20*1.3} -> 614256.5 | M20: {=H20-E20*D20} -> -31124.39 | N20: {=J20-E20*D20} -> 63376.61 | O20: {=K20-E20*D20} -> 134252.36 | P20: {=L20-E20*D20} -> 205128.11
B21: BANKBARODA | C21: BANKING | D21: 1500 | E21: 241.5191 | F21: {=_xlfn.IFERROR(VLOOKUP(B21,'📥 Price Hub'!$B$5:$H$34,7,0),0)} -> 299.3 | G21: {=D21*F21} -> 448950 | H21: {=G21*0.8} -> 359160 | I21: {=G21*0.9} -> 404055 | J21: {=G21} -> 448950 | K21: {=G21*1.15} -> 516292.5 | L21: {=G21*1.3} -> 583635 | M21: {=H21-E21*D21} -> -3118.65 | N21: {=J21-E21*D21} -> 86671.35 | O21: {=K21-E21*D21} -> 154013.85 | P21: {=L21-E21*D21} -> 221356.35
B22: CREDITACC | C22: MICROFINANCE | D22: 350 | E22: 961.5244 | F22: {=_xlfn.IFERROR(VLOOKUP(B22,'📥 Price Hub'!$B$5:$H$34,7,0),0)} -> 1225.8 | G22: {=D22*F22} -> 429030 | H22: {=G22*0.8} -> 343224 | I22: {=G22*0.9} -> 386127 | J22: {=G22} -> 429030 | K22: {=G22*1.15} -> 493384.5 | L22: {=G22*1.3} -> 557739 | M22: {=H22-E22*D22} -> 6690.46 | N22: {=J22-E22*D22} -> 92496.46 | O22: {=K22-E22*D22} -> 156850.96 | P22: {=L22-E22*D22} -> 221205.46
B23: LT | C23: ENGINEERING & CAPITAL GOODS | D23: 110 | E23: 3614.1977 | F23: {=_xlfn.IFERROR(VLOOKUP(B23,'📥 Price Hub'!$B$5:$H$34,7,0),0)} -> 3882.6 | G23: {=D23*F23} -> 427086 | H23: {=G23*0.8} -> 341668.8 | I23: {=G23*0.9} -> 384377.4 | J23: {=G23} -> 427086 | K23: {=G23*1.15} -> 491148.9 | L23: {=G23*1.3} -> 555211.8 | M23: {=H23-E23*D23} -> -55892.947 | N23: {=J23-E23*D23} -> 29524.253 | O23: {=K23-E23*D23} -> 93587.153 | P23: {=L23-E23*D23} -> 157650.05
B24: NH | C24: HEALTHCARE | D24: 240 | E24: 1336.4402 | F24: {=_xlfn.IFERROR(VLOOKUP(B24,'📥 Price Hub'!$B$5:$H$34,7,0),0)} -> 1744 | G24: {=D24*F24} -> 418560 | H24: {=G24*0.8} -> 334848 | I24: {=G24*0.9} -> 376704 | J24: {=G24} -> 418560 | K24: {=G24*1.15} -> 481344 | L24: {=G24*1.3} -> 544128 | M24: {=H24-E24*D24} -> 14102.352 | N24: {=J24-E24*D24} -> 97814.352 | O24: {=K24-E24*D24} -> 160598.35 | P24: {=L24-E24*D24} -> 223382.35
B25: HDFCBANK | C25: BANKING | D25: 450 | E25: 626.6593 | F25: {=_xlfn.IFERROR(VLOOKUP(B25,'📥 Price Hub'!$B$5:$H$34,7,0),0)} -> 868.65 | G25: {=D25*F25} -> 390892.5 | H25: {=G25*0.8} -> 312714 | I25: {=G25*0.9} -> 351803.25 | J25: {=G25} -> 390892.5 | K25: {=G25*1.15} -> 449526.38 | L25: {=G25*1.3} -> 508160.25 | M25: {=H25-E25*D25} -> 30717.315 | N25: {=J25-E25*D25} -> 108895.82 | O25: {=K25-E25*D25} -> 167529.69 | P25: {=L25-E25*D25} -> 226163.57
... B40: SGB-COMBINED | C40: SOVEREIGN GOLD BOND | D40: 6 | E40: 16262.96 | F40: {=_xlfn.IFERROR(VLOOKUP(B40,'📥 Price Hub'!$B$5:$H$34,7,0),0)} -> 16392.83 | G40: {=D40*F40} -> 98356.98 | H40: {=G40*0.8} -> 78685.584 | I40: {=G40*0.9} -> 88521.282 | J40: {=G40} -> 98356.98 | K40: {=G40*1.15} -> 113110.53 | L40: {=G40*1.3} -> 127864.07 | M40: {=H40-E40*D40} -> -18892.176 | N40: {=J40-E40*D40} -> 779.22 | O40: {=K40-E40*D40} -> 15532.767 | P40: {=L40-E40*D40} -> 30286.314
D41: 0
D42: 0
B45: * LTCG at 12.5% on LT gains >₹1.25L exemption. Estimates only — consult tax advisor.

Sheet 🏭 Sector Analysis
B1: SECTOR BREAKDOWN — 15 SUB-SECTORS
B2: Finance split: Banking · Consumer Lending · Housing Finance · Microfinance · Market Infrastructure
B4: Sector | C4: Holdings | D4: Invested (₹) | E4: Mkt Value (₹) | F4: P&L (₹) | G4: Return % | H4: Portfolio Wt
B5: · BANKING | C5: {=COUNTIF('📊 Portfolio Brief'!$C$11:$C$39,"BANKING")} -> 3 | D5: {=SUMIF('📊 Portfolio Brief'!$C$11:$C$39,"BANKING",'📊 Portfolio Brief'!$G$11:$G$39)} -> 1077120.4 | E5: {=SUMIF('📊 Portfolio Brief'!$C$11:$C$39,"BANKING",'📊 Portfolio Brief'!$H$11:$H$39)} -> 1351867.5 | F5: {=E5-D5} -> 274747.07 | G5: {=IF(D5=0,0,F5/D5)} -> 0.25507553 | H5: {=IF(SUM(E5:E19)=0,0,E5/SUM(E5:E19))} -> 0.13358607
B6: · MICROFINANCE | C6: {=COUNTIF('📊 Portfolio Brief'!$C$11:$C$39,"MICROFINANCE")} -> 3 | D6: {=SUMIF('📊 Portfolio Brief'!$C$11:$C$39,"MICROFINANCE",'📊 Portfolio Brief'!$G$11:$G$39)} -> 1066485.9 | E6: {=SUMIF('📊 Portfolio Brief'!$C$11:$C$39,"MICROFINANCE",'📊 Portfolio Brief'!$H$11:$H$39)} -> 1264826 | F6: {=E6-D6} -> 198340.09 | G6: {=IF(D6=0,0,F6/D6)} -> 0.18597536 | H6: {=IF(SUM(E5:E19)=0,0,E6/SUM(E5:E19))} -> 0.12498498
B7: ETF | C7: {=COUNTIF('📊 Portfolio Brief'!$C$11:$C$39,"ETF")} -> 2 | D7: {=SUMIF('📊 Portfolio Brief'!$C$11:$C$39,"ETF",'📊 Portfolio Brief'!$G$11:$G$39)} -> 789934.4 | E7: {=SUMIF('📊 Portfolio Brief'!$C$11:$C$39,"ETF",'📊 Portfolio Brief'!$H$11:$H$39)} -> 1241900 | F7: {=E7-D7} -> 451965.6 | G7: {=IF(D7=0,0,F7/D7)} -> 0.57215587 | H7: {=IF(SUM(E5:E19)=0,0,E7/SUM(E5:E19))} -> 0.12271953
B8: HEALTHCARE | C8: {=COUNTIF('📊 Portfolio Brief'!$C$11:$C$39,"HEALTHCARE")} -> 3 | D8: {=SUMIF('📊 Portfolio Brief'!$C$11:$C$39,"HEALTHCARE",'📊 Portfolio Brief'!$G$11:$G$39)} -> 899577.31 | E8: {=SUMIF('📊 Portfolio Brief'!$C$11:$C$39,"HEALTHCARE",'📊 Portfolio Brief'!$H$11:$H$39)} -> 973084.5 | F8: {=E8-D8} -> 73507.189 | G8: {=IF(D8=0,0,F8/D8)} -> 0.081713031 | H8: {=IF(SUM(E5:E19)=0,0,E8/SUM(E5:E19))} -> 0.096156268
B9: FMCG | C9: {=COUNTIF('📊 Portfolio Brief'!$C$11:$C$39,"FMCG")} -> 2 | D9: {=SUMIF('📊 Portfolio Brief'!$C$11:$C$39,"FMCG",'📊 Portfolio Brief'!$G$11:$G$39)} -> 759780.75 | E9: {=SUMIF('📊 Portfolio Brief'!$C$11:$C$39,"FMCG",'📊 Portfolio Brief'!$H$11:$H$39)} -> 814065 | F9: {=E9-D9} -> 54284.25 | G9: {=IF(D9=0,0,F9/D9)} -> 0.071447256 | H9: {=IF(SUM(E5:E19)=0,0,E9/SUM(E5:E19))} -> 0.080442606
B10: · CONSUMER LENDING | C10: {=COUNTIF('📊 Portfolio Brief'!$C$11:$C$39,"CONSUMER LENDING")} -> 1 | D10: {=SUMIF('📊 Portfolio Brief'!$C$11:$C$39,"CONSUMER LENDING",'📊 Portfolio Brief'!$G$11:$G$39)} -> 495000 | E10: {=SUMIF('📊 Portfolio Brief'!$C$11:$C$39,"CONSUMER LENDING",'📊 Portfolio Brief'!$H$11:$H$39)} -> 708825 | F10: {=E10-D10} -> 213825 | G10: {=IF(D10=0,0,F10/D10)} -> 0.4319697 | H10: {=IF(SUM(E5:E19)=0,0,E10/SUM(E5:E19))} -> 0.070043215
B11: ENGINEERING & CAPITAL GOODS | C11: {=COUNTIF('📊 Portfolio Brief'!$C$11:$C$39,"ENGINEERING & CAPITAL GOODS")} -> 2 | D11: {=SUMIF('📊 Portfolio Brief'!$C$11:$C$39,"ENGINEERING & CAPITAL GOODS",'📊 Portfolio Brief'!$G$11:$G$39)} -> 570392.04 | E11: {=SUMIF('📊 Portfolio Brief'!$C$11:$C$39,"ENGINEERING & CAPITAL GOODS",'📊 Portfolio Brief'!$H$11:$H$39)} -> 682056 | F11: {=E11-D11} -> 111663.96 | G11: {=IF(D11=0,0,F11/D11)} -> 0.19576704 | H11: {=IF(SUM(E5:E19)=0,0,E11/SUM(E5:E19))} -> 0.067398011
B12: · HOUSING FINANCE | C12: {=COUNTIF('📊 Portfolio Brief'!$C$11:$C$39,"HOUSING FINANCE")} -> 2 | D12: {=SUMIF('📊 Portfolio Brief'!$C$11:$C$39,"HOUSING FINANCE",'📊 Portfolio Brief'!$G$11:$G$39)} -> 587559.04 | E12: {=SUMIF('📊 Portfolio Brief'!$C$11:$C$39,"HOUSING FINANCE",'📊 Portfolio Brief'!$H$11:$H$39)} -> 675936.65 | F12: {=E12-D12} -> 88377.608 | G12: {=IF(D12=0,0,F12/D12)} -> 0.15041486 | H12: {=IF(SUM(E5:E19)=0,0,E12/SUM(E5:E19))} -> 0.066793322
B13: SOFTWARE SERVICES | C13: {=COUNTIF('📊 Portfolio Brief'!$C$11:$C$39,"SOFTWARE SERVICES")} -> 3 | D13: {=SUMIF('📊 Portfolio Brief'!$C$11:$C$39,"SOFTWARE SERVICES",'📊 Portfolio Brief'!$G$11:$G$39)} -> 629447.28 | E13: {=SUMIF('📊 Portfolio Brief'!$C$11:$C$39,"SOFTWARE SERVICES",'📊 Portfolio Brief'!$H$11:$H$39)} -> 555600 | F13: {=E13-D13} -> -73847.28 | G13: {=IF(D13=0,0,F13/D13)} -> -0.11732083 | H13: {=IF(SUM(E5:E19)=0,0,E13/SUM(E5:E19))} -> 0.054902141
B14: METALS | C14: {=COUNTIF('📊 Portfolio Brief'!$C$11:$C$39,"METALS")} -> 1 | D14: {=SUMIF('📊 Portfolio Brief'!$C$11:$C$39,"METALS",'📊 Portfolio Brief'!$G$11:$G$39)} -> 466703.28 | E14: {=SUMIF('📊 Portfolio Brief'!$C$11:$C$39,"METALS",'📊 Portfolio Brief'!$H$11:$H$39)} -> 522180 | F14: {=E14-D14} -> 55476.72 | G14: {=IF(D14=0,0,F14/D14)} -> 0.11886936 | H14: {=IF(SUM(E5:E19)=0,0,E14/SUM(E5:E19))} -> 0.051599712
B15: DEFENCE | C15: {=COUNTIF('📊 Portfolio Brief'!$C$11:$C$39,"DEFENCE")} -> 1 | D15: {=SUMIF('📊 Portfolio Brief'!$C$11:$C$39,"DEFENCE",'📊 Portfolio Brief'!$G$11:$G$39)} -> 377433.11 | E15: {=SUMIF('📊 Portfolio Brief'!$C$11:$C$39,"DEFENCE",'📊 Portfolio Brief'!$H$11:$H$39)} -> 373331.25 | F15: {=E15-D15} -> -4101.8625 | G15: {=IF(D15=0,0,F15/D15)} -> -0.010867787 | H15: {=IF(SUM(E5:E19)=0,0,E15/SUM(E5:E19))} -> 0.036891082
B16: FERTILIZERS | C16: {=COUNTIF('📊 Portfolio Brief'!$C$11:$C$39,"FERTILIZERS")} -> 1 | D16: {=SUMIF('📊 Portfolio Brief'!$C$11:$C$39,"FERTILIZERS",'📊 Portfolio Brief'!$G$11:$G$39)} -> 401518.66 | E16: {=SUMIF('📊 Portfolio Brief'!$C$11:$C$39,"FERTILIZERS",'📊 Portfolio Brief'!$H$11:$H$39)} -> 366605 | F16: {=E16-D16} -> -34913.665 | G16: {=IF(D16=0,0,F16/D16)} -> -0.086954027 | H16: {=IF(SUM(E5:E19)=0,0,E16/SUM(E5:E19))} -> 0.036226421
B17: · MARKET INFRASTRUCTURE | C17: {=COUNTIF('📊 Portfolio Brief'!$C$11:$C$39,"MARKET INFRASTRUCTURE")} -> 1 | D17: {=SUMIF('📊 Portfolio Brief'!$C$11:$C$39,"MARKET INFRASTRUCTURE",'📊 Portfolio Brief'!$G$11:$G$39)} -> 317821.01 | E17: {=SUMIF('📊 Portfolio Brief'!$C$11:$C$39,"MARKET INFRASTRUCTURE",'📊 Portfolio Brief'!$H$11:$H$39)} -> 283657.5 | F17: {=E17-D17} -> -34163.505 | G17: {=IF(D17=0,0,F17/D17)} -> -0.10749291 | H17: {=IF(SUM(E5:E19)=0,0,E17/SUM(E5:E19))} -> 0.028029885
B18: ENERGY | C18: {=COUNTIF('📊 Portfolio Brief'!$C$11:$C$39,"ENERGY")} -> 1 | D18: {=SUMIF('📊 Portfolio Brief'!$C$11:$C$39,"ENERGY",'📊 Portfolio Brief'!$G$11:$G$39)} -> 253654.62 | E18: {=SUMIF('📊 Portfolio Brief'!$C$11:$C$39,"ENERGY",'📊 Portfolio Brief'!$H$11:$H$39)} -> 207532.5 | F18: {=E18-D18} -> -46122.125 | G18: {=IF(D18=0,0,F18/D18)} -> -0.18183041 | H18: {=IF(SUM(E5:E19)=0,0,E18/SUM(E5:E19))} -> 0.020507521
B19: SOVEREIGN GOLD BOND | C19: {=COUNTIF('📊 Portfolio Brief'!$C$11:$C$39,"SOVEREIGN GOLD BOND")} -> 1 | D19: {=SUMIF('📊 Portfolio Brief'!$C$11:$C$39,"SOVEREIGN GOLD BOND",'📊 Portfolio Brief'!$G$11:$G$39)} -> 97577.76 | E19: {=SUMIF('📊 Portfolio Brief'!$C$11:$C$39,"SOVEREIGN GOLD BOND",'📊 Portfolio Brief'!$H$11:$H$39)} -> 98356.98 | F19: {=E19-D19} -> 779.22 | G19: {=IF(D19=0,0,F19/D19)} -> 0.0079856312 | H19: {=IF(SUM(E5:E19)=0,0,E19/SUM(E5:E19))} -> 0.0097192383
B21: TOTAL FINANCE EXPOSURE | C21: {=SUM(C5,C6,C10,C12,C17)} -> 10 | D21: {=SUM(D5,D6,D10,D12,D17)} -> 3543986.4 | E21: {=SUM(E5,E6,E10,E12,E17)} -> 4285112.6 | F21: {=E21-D21} -> 741126.26 | G21: {=IF(D21=0,0,F21/D21)} -> 0.20912221 | H21: {=IF(SUM(E5:E19)=0,0,E21/SUM(E5:E19))} -> 0.42343747
B23: GRAND TOTAL | C23: 29 | D23: {=SUM(D5:D22)} -> 12333992 | E23: {=SUM(E5:E22)} -> 14404936 | F23: {=E23-D23} -> 2070944.5 | G23: {=F23/D23} -> 0.16790545 | H23: 1

Sheet 💻 IT Sector Analysis
B2: 💻 IT SECTOR — Sell-off Analysis & Portfolio Positioning | 6 March 2026
B3: Is the broad-based selling structural or panic? Where does the portfolio sit? What is the right action?
B6: CONFIRMED: Broad-based FII + Retail selling | C6: Nifty IT fell ~20% in February 2026 — worst monthly fall since March 2020. ₹5.7 lakh crore in market cap erased in under two weeks. FPIs pulled ₹10,956Cr from IT in just the first half of February. Total FII IT outflow in 2025: ₹74,698Cr — 8 months of sustained, deliberate sector deweight. FII holdings in IT at a 4-year low. Infosys FII stake: 30.68%, HCL Tech: 16.2%. Retail also selling: domestic MF IT allocation at ~8% vs ~9% index weight — even MFs are underweight. DII buying has NOT absorbed the FII selling. This is both institutional AND retail — broad-based confirmed.
B7: THE TRIGGER — 'Anthropic Shock' | C7: Market participants are using the term 'Anthropic shock' for the Feb 2026 sell-off trigger: Anthropic enterprise AI workplace tools + Palantir releases intensified fears that generative AI automates Application Development & Maintenance — the backbone of Indian IT billing. Infosys ADR fell 10% in a single US session, cascading to NSE. The fear is real for the WRONG companies. T&M billing models with 60%+ entry-level headcount (TCS, Infosys, Wipro, Tech Mahindra) ARE structurally at risk. AI does substitute junior code-level work billed per hour. Motilal Oswal estimates 9–12% of IT services revenue at risk over 3–4 years for these models.
B8: THE BIFURCATION — Who is wrongly caught | C8: DISRUPTED (right to sell): · TCS, Infosys, Wipro, Tech Mahindra · T&M billing, 60%+ junior headcount, commoditised ADM work · TCS revenue/employee flat at ~$49K for a decade — AI compounds stagnation · These names absorb the 9–12% revenue risk directly SAFE / BENEFICIARY (wrongly sold): · Persistent: SASVA platform generates NET-NEW AI revenue, not compressing existing. Microsoft Frontier Firm. 23 consecutive growth quarters. $674.5M TCV Q3 FY26. · eClerx: Domain KPO — capital markets trade lifecycle, compliance, financial analytics. Human judgment required. AI-resistant at the core. · Sagility: US healthcare BPO. AI processes more claims faster = Sagility wins MORE volume. 35.7% Q3 revenue growth. The sell-off is painting all three with the same brush as TCS. That is the mispricing.
B9: SMART MONEY — What is actually happening | C9: After 6 weeks of sustained selling, selective accumulation has begun in platform/domain IT: · Persistent at 52x P/E vs historical 60–70x during growth phases — delivering 17%+ growth · eClerx: promoter completed ₹300Cr buyback at ₹4,800. CMP ₹3,222. Founder sees deep value. · Nifty IT select stocks at 8-year valuation lows despite fundamentally different earnings profiles The divergence is becoming visible: generics (TCS, Infy) continue to be sold. Specialists (Persistent, eClerx) are finding institutional floors. This transition typically takes 2–3 quarters to fully play out in price.
B10: YOUR IT BOOK — 3 positions, 3 distinct sub-theses | C10: eClerx (held, ₹3,222): → Domain KPO. Capital markets operations, trade lifecycle, financial analytics. Requires domain judgment — AI cannot fully automate compliance calls, error resolution in trade execution, structured product analytics. Promoter at 54.5% bought back at ₹4,800 vs CMP ₹3,222. That 33% gap IS the signal. Add modestly — this is the clearest conviction buy in the IT space right now. Persistent (40-share tracker, in loss): → SASVA platform, 23 quarters growth, Microsoft Frontier Firm, $674.5M TCV. The business is fine — the stock is caught in sector panic. Decision still stands: proper re-entry (sell tracker, buy 80–100 shares as a real 3% position) OR clean exit. Do NOT add to a tracker. Do NOT exit just because of this crash. Sagility (planned addition with LT proceeds): → Healthcare BPO. AI accelerates their business, not disrupts it. Q3 FY26 revenue ₹1,971Cr, best ever. 35.7% YoY growth. FY26 guidance raised to 22.5% CC growth. ICICI Sec target ₹76 (+55%). The IT sell-off has kept Sagility near ₹50 — excellent entry window.
B11: ACTION SUMMARY | C11: eClerx: HOLD + MODEST ADD at CMP ₹3,222. Promoter signal anchor at ₹4,800. No cut. Persistent: DECIDE — proper position or clean exit. Not a tracker. The crash widens the re-entry discount. Sagility: PROCEED with LT exit proceeds (~₹4.3L). IT sell-off = better entry than planned. Nifty IT: The panic is the opportunity for the RIGHT names. T&M body shops are rightly sold. Platform + domain = mispriced in the sell-off. Your book is on the correct side.
B13: Sources: NSDL FII data, Business Standard, NSE sector data, Q3 FY26 earnings — Persistent, eClerx, Sagility · 6 Mar 2026

Sheet ⚡ IEX Deep Dive
B2: ⚡ IEX — Deep Dive | Accumulation Thesis | 6 March 2026
B3: Position: INCREASING ALLOCATION · Market is wrong on timing and magnitude of coupling risk · Volume growth ignored · Tainted regulator ignored
B5: CMP ~₹119 · 52W High ₹215 · Down 44.6% from peak · Mkt Cap ~₹10,500Cr · 9M FY26 PAT ₹363Cr · Annualised P/E ~22x · Div Yield ~2.5% · Feb 2026 volume +30.4% YoY — HIGHEST EVER
B7: WHAT IEX ACTUALLY IS — The exchange franchise | C7: IEX is India's electricity exchange — the NSE of power. Not a generator, not a distributor. Pure marketplace. Revenue model: ₹0.02/unit transaction fee. 83% market share in spot electricity trading. Near-zero marginal cost of volume — every additional unit traded goes almost entirely to the bottom line. Operating leverage is extreme: 65%+ EBITDA margins. Network effects: liquidity attracts liquidity, the dominant exchange stays dominant. The core thesis you're acting on: exchanges do not go to zero. India's power demand is structural — industrial growth, EV adoption, data center boom, cooling demand. More power traded = more IEX revenue. The regulatory overhang is real but the business underneath is sound and growing.
B8: THE COUPLING THREAT — Correctly understood | C8: Market coupling: CERC wants price discovery to shift from IEX's own auction to a central pooling algorithm across all exchanges. Under coupling, IEX loses the pricing advantage that keeps 83% of liquidity. Smaller exchanges (PXIL, HPX) could compete on equal terms. This is the real risk — not a fake scare. The market IS right that coupling is negative for IEX. It is WRONG on three things: 1. TIMING — coupling is minimum 18–24 months from March 2026 2. MAGNITUDE — European data shows dominant exchanges retain 55–65% share post-coupling (not 33%) 3. OFFSET — India's power market grows fast enough that absolute volume (and revenue) may not fall even at 60% share
B9: THE TAINTED REGULATOR — The most underpriced factor | C9: SEBI's October 2025 interim order: prima facie evidence that individuals linked to CERC officials used advance knowledge of the July 2025 coupling order to trade IEX put options — illegal gains of ₹173Cr from the resulting stock crash. APTEL acknowledged: 'these allegations if found to be true would cast a cloud on the manner in which an independent regulator functions.' Implications: · The coupling order is legally tainted. It will face rigorous judicial scrutiny on any final notification. · Political will to aggressively enforce a tainted order is reduced. MoP and CERC both know this is a liability. · IEX's legal team has maximum ammunition for any challenge to final regulations. · The SEBI insider trading case creates precedent that CERC exceeded its authority — relevant to any PIL or judicial review. The market is treating the APTEL ruling as 'coupling confirmed.' It should be treating it as 'coupling faces maximum legal headwinds with a tainted genesis.'
B10: THE PILOT DATA — CERC's own evidence | C10: CERC ran a 4-month shadow pilot (Dec 2024–Mar 2025). Results: · DAM coupling welfare gain: ₹38Cr = 0.3% improvement · RTM coupling welfare gain: ₹72 lakh = 0.01% improvement APTEL's own judgment questioned: lack of empirical evidence of market failure, no independent cost-benefit analysis, no stakeholder consensus. A regulator pushed through a massively disruptive policy — splitting liquidity, creating implementation complexity, destroying ₹5.7L Cr in market cap — for 0.3% efficiency gain. This data point matters because: if/when coupling reaches judicial review, this evidence will be front and centre. It makes the reform legally and politically fragile.
B11: VOLUME DATA — The business the market is ignoring | C11: Q3 FY26 (Oct–Dec 2025): · Revenue ₹183.1Cr (+14% YoY) · PAT ₹119.1Cr (+11% YoY) · Electricity traded 34.1 BU (+12% YoY) · 9M FY26 PAT: ₹363Cr (+16.4% YoY) · Interim dividend: ₹1.5/share declared January 2026: 13,050 MU — HIGHEST EVER monthly volume, +19.6% YoY February 2026: 12,550 MU — +30.4% YoY The business is not slowing down ahead of coupling. It is accelerating. Every month of delay in coupling implementation is a month of 12–30% volume growth compounding at near-zero marginal cost. The market has completely decoupled (pun intended) the stock price from the operating performance.
B12: VALUATION — The mispricing quantified | C12: Current: Mkt cap ~₹10,500Cr · Annualised PAT ~₹490Cr · P/E ~22x · Div yield ~2.5% Comparables: · NSE (unlisted): 30–40x P/E · BSE (listed): 35–40x P/E · MCX (commodity exchange): 28–32x P/E · Deutsche Börse post-coupling: re-rated to 28x once volume growth was confirmed IEX at 22x P/E with faster volume growth than any listed Indian exchange, 65%+ EBITDA margin, zero capex, ~2.5% dividend yield — is trading at a 35–40% discount to exchange peers purely on coupling fear. Fair value WITHOUT coupling: ₹200–220 (30–32x PAT) Fair value WITH full base-case coupling (60% share, volume growth offsets): ₹150–175 Fair value catastrophic case (33% share, no growth): ₹40–50 At ₹119, the market is pricing something between base and catastrophic. Given coupling is 18+ months away and volume is +30% YoY, this is excessive pessimism.
B13: ACCUMULATION THESIS — Framing the position | C13: You are increasing allocation. Here is the framework for sizing: CORE THESIS: Own a growing monopoly franchise at a 44% discount from peak, at a P/E below all exchange peers, with a ~2.5% dividend yield while you wait for regulatory clarity. TIME HORIZON: 2–3 years. Coupling implementation + market share settling + volume growth acceleration = re-rating window. POSITION SIZING LOGIC: · Current tracker: 720 LT shares at ₹144.95 avg (~₹1.05L at CMP) · Accumulating: Each tranche should have a clear price anchor. ₹115–120 = strong accumulation zone. If falls to ₹100–105 on further panic = aggressive add zone. · Target weight: Given the risk profile (regulatory binary), 3–4% of portfolio is appropriate. Above 5% = concentrated regulatory risk. DIVIDEND SUPPORT: At ₹119 CMP and historical payout of ₹3–3.5/share annually, yield is ~~2.5%. You are paid to wait. CATALYST SEQUENCE: 1. CERC publishes draft coupling regulations → stock may dip further → BUY 2. Public comment period (60–90 days) → IEX + market participants challenge → legal uncertainty = opportunity 3. Final regulations notified → stock has already priced worst case → relief rally 4. Coupling goes live (2027–28) → volume data shows IEX retains 60%+ → full re-rating
B14: RISK MANAGEMENT — What changes the thesis | C14: THESIS BREAKERS — EXIT if any of these: ✗ CERC notifies final coupling regulations with IMMEDIATE implementation (no phasing) ✗ IEX market share falls below 60% within 6 months of coupling go-live ✗ Monthly volume growth turns negative for 2+ consecutive months (structural demand shift) ✗ IRDAI or MoP takes additional punitive action beyond coupling (fee caps, transaction taxes) ✗ Government mandates renewable energy to bypass exchanges (administrative allocation) THESIS SUPPORTERS — HOLD/ADD if: ✓ Coupling delayed beyond Dec 2027 (most likely base case) ✓ IGX (gas exchange) + ICX (carbon exchange) revenue scaling materially ✓ Monthly volume continues 15%+ YoY growth ✓ Insider trading case leads to CERC leadership change ✓ Any analyst re-rating post coupling timeline clarity
B15: UPDATED POSITION VIEW — Replace exit with accumulation | C15: ORIGINAL PLAN (from consolidation sheet): Exit 720 LT tracker in Wave 2 once CERC draft published. REVISED PLAN (based on your increasing allocation + deep dive): · Remove IEX from the Wave 2 exit list entirely. · 720 LT shares in loss = core position, NOT a tracker. Hold and build. · New purchases at ₹119 and below go in as fresh STCG buckets — separate from the LT book. · Target: 3–4% portfolio weight. Currently ~2% post Wave 1 trim. · Accumulation zones: ₹115–120 (current), ₹100–105 (panic add). · Collect ₹3–3.5/share dividend annually (~2.5% yield). Compounds the wait. · Exit trigger is thesis-break (see above), NOT coupling timeline. The consolidation plan will be updated to reflect: IEX = HOLD + ACCUMULATE, removed from exit list.
B17: Sources: IEX Q3 FY26 earnings call, APTEL order Feb 13 2026, SEBI interim order Oct 2025, CERC pilot data, Bernstein/JM Financial notes, BSE/NSE exchange comparables · 6 Mar 2026

Sheet 🔍 IT Deep Dive
B1: IT SECTOR DEEP DIVE — AI DISRUPTION ANALYSIS
B2: The sector sell-off paints all IT with one brush. The opportunity is separating genuine AI beneficiaries from disrupted models.
B4: MACRO CONTEXT — WHAT IS ACTUALLY HAPPENING
B5: 1. Nifty IT fell 6% in its worst session in ~6 years after Anthropic/Palantir releases — sector-wide indiscriminate sell-off.
B6: 2. Motilal Oswal estimates AI eliminates 9–12% of IT services revenue over 3–4 years. But only ~20% of embedded effort is truly at risk.
B7: 3. The DISRUPTED model: Time & Material billing, 60%+ entry-level headcount. TCS revenue/employee flat at ~$49K for a decade.
B8: 4. The SAFE model: Outcome-based, platform-led, domain-specialist. These companies are AI beneficiaries, not victims.
B9: 5. Opportunity: Indiscriminate sell-off creates mispricing in names on the RIGHT side of the AI transition.
B11: PERSISTENT — IN PORTFOLIO — SOLD AT LOSS — CONSIDER RE-ENTRY
B12: CMP: ₹4,709 | Avg: ₹5,143 | D12: Verdict: Best-positioned Indian IT name for the AI era. Sector sell-off is macro fear, not fundamental.
B13: 🐂 Bull (55%) Target: ₹6,500–7,000 | D13: 📊 Base (35%) Target: ₹5,200–5,800 | F13: 🐻 Bear (10%) Target: ₹3,800–4,200
B14: WHY IT WORKS — BULL CASE
B15: ✓ 23rd consecutive quarter of sequential revenue growth at 17.3% YoY — while peers are flat/declining.
B16: ✓ Microsoft Frontier Firm recognition = highest-tier AI integration validation. Not a marketing badge.
B17: ✓ SASVA AI platform generates NET NEW revenue by expanding scope of bids — not compressing existing economics.
B18: ✓ Order booking $674.5M TCV / $501.9M ACV in Q3 FY26. Multi-year AI/cloud engagements.
B19: ✓ Europe growing 37%+ YoY. Geographic diversification reducing US concentration.
B20: ✓ Management targeting $2B revenue by FY27 at 18–19% CC CAGR — credible given 23-quarter track record.
B21: ✓ Stock fell from ₹6,200 → ₹4,709 on sector rotation alone. Zero fundamental deterioration.
B22: KEY RISKS
B23: ✗ High valuation premium vs peers — guidance cut would be punished severely.
B24: ✗ US macro slowdown hits discretionary IT spending first.
B27: ECLERX — IN PORTFOLIO — HOLD, CONSIDER MODEST ADD
B28: CMP: ₹3,222 | Avg: ₹3,310 | D28: Verdict: Domain-specialist KPO. Promoter bought back at ₹4,800. CMP ₹3,222. That gap is the signal.
B29: 🐂 Bull (45%) Target: ₹4,500–5,000 | D29: 📊 Base (40%) Target: ₹3,600–4,000 | F29: 🐻 Bear (15%) Target: ₹2,600–2,900
B30: WHY IT WORKS — BULL CASE
B31: ✓ KPO not generic IT — Capital Markets operations, trade lifecycle, financial analytics. Domain judgment required.
B32: ✓ Promoter at 54.52% post-buyback. Completed ₹300Cr buyback at ₹4,800 vs CMP ₹3,222 — promoter sees deep value.
B33: ✓ Everest Group Leader + Star Performer in Capital Markets Operations PEAK Matrix 2025.
B34: ✓ 5 AI solutions built including GenAI360. Investing ahead of curve in domain-specific AI.
B35: ✓ Client base = global investment banks. High switching cost, sticky multi-year relationships.
B36: ✓ AI risk much lower than peers — domain judgment (trade errors, compliance) harder to fully automate.
B37: KEY RISKS
B38: ✗ Global bank client concentration — if banks build in-house AI capability, pressure on outsourced work.
B39: ✗ US financial sector slowdown reduces transaction volumes.
B42: SAGILITY — NOT IN PORTFOLIO — WATCHLIST / CONSIDER ENTRY
B43: CMP: ₹50 | Not currently held | D43: Verdict: US healthcare BPO where AI ACCELERATES not disrupts. Pure-play on a $200B TAM growing structurally.
B44: 🐂 Bull (50%) Target: ₹75–85 | D44: 📊 Base (35%) Target: ₹58–68 | F44: 🐻 Bear (15%) Target: ₹35–40
B45: WHY IT WORKS — BULL CASE
B46: ✓ Pure-play US healthcare BPO: claims processing, revenue cycle management, clinical documentation.
B47: ✓ TAM = $200B US healthcare admin. US spends $5T on healthcare growing to $6.1T by 2028 at 5.5% CAGR.
B48: ✓ AI HELPS not hurts: AI tools process more claims faster at lower cost — Sagility wins more volume, not less.
B49: ✓ India cost advantage ~40% vs onshore delivery. India = 40–45% of global healthcare BPO.
B50: ✓ Broadpath Healthcare acquisition (Jan 2025) adds provider-side to existing payer strength.
B51: ✓ Motilal Oswal Buy rating on structural tailwinds. TTM revenue $773M at ~$2.57B mkt cap = 3.3x revenue.
B52: KEY RISKS
B53: ✗ US healthcare policy restructuring (ACA changes) = direct TAM risk. Key monitor.
B54: ✗ EQT PE promoter (Sagility BV) — eventual exit overhang.
B55: ✗ Client concentration in large US health insurers.

Sheet 💊 Medi Assist
B1: MEDI ASSIST HEALTHCARE SERVICES — DEEP DIVE
B2: TPA market leader. MIT endowment signal. Bought on watchlist, building conviction position.
B4: INVESTMENT CONTEXT
B5: 1. India health insurance penetration remains very low. TPA industry consolidates around the dominant player — Medi Assist.
B6: 2. Paramount acquisition (closed July 2025) adds ₹4,000Cr health premiums under administration. Group segment market share now 36.6%, total industry ~23.6%.
B7: 3. MIT Investment Management (MITIMCo) invested ₹198Cr via preferential allotment at ₹535/share. A $27.4B endowment doing a direct pref allotment in a mid-cap Indian TPA is a highly deliberate, research-heavy decision.
B8: 4. MIT is a 10-year+ investor. They are underwater at ₹535 vs CMP ~₹340 — they will add or hold, not sell. This is a structural anchor, not a short-term trade.
B9: 5. Bessemer India exited 15.7% stake in Aug 2025 at ₹577Cr — founding VC full exit is the primary overhang. Monitor whether other institutional holders follow or hold.
B11: MEDIASSIST — IN PORTFOLIO — ACCUMULATE | TARGET 6–7%
B12: Qty | C12: Avg Cost | D12: CMP | E12: Invested | F12: Mkt Value | G12: P&L | H12: Return | I12: LT Qty
B13: 700 | C13: ₹416.16 | D13: ₹340.50 | E13: ₹291,312 | F13: ₹238,350 | G13: ₹-52,962 | H13: -18.2% | I13: 0
B14: 📌 Stock is down on integration noise and one-offs. The underlying franchise is strengthening. MIT at ₹535 gives you a quality anchor well above your potential accumulation price.
B15: 🐂 Bull (45%) Target: ₹620–700 | D15: 📊 Base (35%) Target: ₹420–480 | F15: 🐻 Bear (20%) Target: ₹240–270
B16: BULL CASE — WHY THE THESIS IS INTACT
B17: ✓ Market share in group segment grew from 23.5% (FY20) to 30%+ (FY24) before Paramount — structurally widening moat.
B18: ✓ Post-Paramount: group segment share 36.6%, total industry ~23.6% of premiums under management. Market share is widening even as P&L looks messy.
B19: ✓ Fraud Detection Engine identified ~₹400Cr in fraud, waste and abuse for insurers in FY25. AI tool improving 1.5x YoY. Star Health — a direct competitor — chose to outsource claims to Medi Assist platform. That is the clearest possible validation of the tech moat.
B20: ✓ Q3 FY26: 24% revenue growth. Company became DEBT-FREE from January 2026. Balance sheet is clean going into the growth phase.
B21: ✓ PAT plunge of 86% YoY was due to exceptional items (Paramount cybersecurity costs + claim provisions). Adjusted 9M FY26 operating PAT was ₹46.3Cr — underlying business is fine.
B22: ✓ On clean FY27 PAT estimate ₹90–100Cr, stock trades at 27–30x — reasonable for a dominant platform growing 20%+ with no debt.
B23: ✓ Keynote Capital initiated with ₹707 target (from ₹468 at initiation). From ₹340 today = ~108% upside in the bull case.
B24: KEY RISKS — WHAT TO WATCH
B25: ✗ ED search at Ranchi (alleged Ayushman Bharat irregularities) — single biggest tail risk. If escalates to formal charges or IRDAI licence action, business model directly threatened. Track quarterly.
B26: ✗ Maharashtra GST department search at Mumbai TPA subsidiary office (Feb 2026) — proceedings ongoing.
B27: ✗ Promoter holding only 4.62% — effectively no promoter skin in the game. Management continuity risk.
... B36: → Key monitors: FII holding trend (watch for further exits), employee cost as % of revenue (should fall below 40%), ED/GST status.

Sheet 📈 MEDIASSIST Technical
B2: 📈 MEDIASSIST — Technical Analysis | Chart Structure & Entry Framework
B3: Yes it looks brutal. Here is exactly why, what the structure means, and what to watch for.
B5: ATH ₹716 (Sep 2024) → IPO listing ₹535 area → MIT entry ₹535 (Oct 2025) → 52W low ₹385 (Apr 2025) → Brief recovery ₹594 → Current ~₹340 → YOUR AVG ₹416 → Down 44% from ATH
B6: THE CHART STRUCTURE — Why it looks brutal | C6: MEDIASSIST listed January 2024 at ~₹635 (GMP-inflated open). The stock: · Peaked at ₹716 in Sep 2024 (pre-Paramount, clean earnings) · Fell to ₹415 in April 2025 — first 52W low — as Paramount integration costs hit · Recovered to ₹594 briefly in July 2025 on MIT investment news · Rolled over again on Bessemer exit (Aug 2025, ₹15.7% stake sold) · GST/ED news in Feb 2026 knocked it to ₹385 region · Current CMP ~₹340 (as of session) — BELOW the April 2025 52W low Structure: A clean downtrend of LOWER HIGHS + LOWER LOWS since Sep 2024. Every rally has been sold. This is a stock in a confirmed intermediate downtrend. The 'brutal' read is technically correct — this is not a chart that has bottomed yet on pure price action alone.
B7: KEY PRICE LEVELS — The map | C7: RESISTANCE (overhead supply — where sellers emerge): ₹395–400 — recent breakdown level, now resistance. Stock was ₹396 on Feb 16. ₹415–420 — previous 52W low (Apr 2025), now resistance. Strong supply zone. ₹460–480 — Jan 2026 consolidation zone. Heavy volume traded here. ₹530–535 — MIT entry price. Psychological + technical resistance. Also Bessemer exit zone. ₹594 — July 2025 relief rally high. Major resistance. SUPPORT (where buying may emerge): ₹320–330 — visible support from Dec 2023 / IPO range congestion zone ₹300–310 — round number + listing-day low region. Last line before price discovery. ₹280–290 — if ₹300 breaks, next meaningful technical floor YOUR POSITION: avg ₹416 is now ABOVE the primary resistance cluster. You are underwater and the resistance overhead is dense.
B8: VOLUME & SENTIMENT SIGNALS | C8: NEGATIVE signals visible in chart data: · Strong Sell on daily moving average signals (Investing.com technical rating) · Stock making new 52W lows through Feb-Mar 2026 — no climactic capitulation volume seen yet · Bessemer exit (largest institutional seller) completed Aug 2025 but overhang from other PE holders possible · Beta 0.84 — relatively low beta but stock has been a consistent underperformer vs index POSITIVE signals: · MIT buying at ₹535 in Oct 2025 = fresh institutional accumulation AFTER Bessemer exit — smart money stepped in · 3 analyst Buy ratings, avg target ₹636 (+87% from ₹340) — zero Sell ratings · Promoter reclassification (Jan 2026) is housekeeping, not exit · Debt-free from Jan 2026 confirmed — balance sheet inflection · Revenue run-rate ₹960Cr+ annualised — business is growing despite chart pain
B9: WHAT WOULD A BOTTOM LOOK LIKE | C9: Bottoms in stocks with genuine business value tend to form when: 1. CAPITULATION VOLUME: A high-volume sell day (3–5x average) on bad news, then reversal. Has NOT happened yet — the decline has been grinding, not panicky. Capitulation would be a day where the stock drops 8–10% on news then reverses and closes near the high. Watch for this. 2. NEGATIVE NEWS ABSORBED: When ED + GST headlines no longer drop the stock. The stock is starting to show this — GST resolved (paid ₹4.83Cr), stock didn't crater on that news. IRDAI renewal (Mar 20) is the next binary. 3. TECHNICAL BASE: Minimum 4–6 weeks of sideways action in a tight range (₹320–360 zone) with declining volume. Stock is still in a slope — not basing yet. 4. CATALYST REVERSAL: Q4 FY26 results (May 2026) showing first clean quarter post-Paramount. That is the earliest a fundamental re-rating can begin. Current assessment: NOT YET BOTTOMED on technicals. But approaching the zone where capitulation becomes possible.
B10: THE ACCUMULATION FRAMEWORK — Entry zones | C10: Given the fundamental thesis is intact (MIT at ₹535, platform moat, debt-free), the approach is: ZONE 1 — ₹330–350 (current): ACCUMULATE SMALL. You are already in at ₹416 avg. Additional purchases here are averaging down. Each tranche should be small (~10–15% of planned total add). This zone is still in downtrend but offers a fundamental margin of safety vs MIT's ₹535. ZONE 2 — ₹300–320 (on panic): ACCUMULATE MORE AGGRESSIVELY. If IRDAI news, Q3 results or macro triggers a flush to ₹300, that is the maximum pain zone and historically the best entry in fundamental dip-buys. If this level holds, it's the base. ZONE 3 — ₹280 or below (catastrophe): PAUSE. At this level, re-evaluate whether ED/IRDAI has escalated to something structural. Do not blindly average below ₹280 without fresh fundamental check. CONFIRMED REVERSAL SIGNAL: Stock breaking and holding ABOVE ₹415–420 on meaningful volume (2x average) = technical trend change. That is when you add the largest tranche. Do not chase — wait for the trend to turn.
B11: UPDATED ACCUMULATION PLAN | C11: TRANCHE PLAN (revised for technical reality): T1 — ✅ IRDAI CONFIRMED (Mar 20 passed): Licence renewed — first binary cleared. This removes the biggest immediate tail risk and validates the accumulation case. T2 — ACCUMULATE NOW (post-IRDAI): Add ~₹1L at current levels (₹330–350). IRDAI cleared. This is the first tranche entry window. Use Zydus + Rainbow proceeds. T3 — Q4 FY26 RESULTS (May 2026): Add ~₹1.5L if results show (a) clean PAT recovery, (b) employee costs below 40% of revenue, (c) no new regulatory actions. This is the fundamental pivot quarter. T4 — ED CLOSURE (timeline unknown): Add ~₹1.5L on formal ED proceedings close. This removes the largest permanent risk discount. T5 — TECHNICAL BREAKOUT above ₹415: Add ~₹1L on trend confirmation. Biggest tranche reserved for when the chart confirms the fundamental thesis. Target weight: 6–7% at full allocation. Currently 2.4%. The brutal chart is the OPPORTUNITY — but respect the downtrend. Do not front-run the bottom.
B13: Sources: TradingView MEDIASSIST chart, Investing.com technical ratings, IndMoney 52W data, Q3 FY26 filings · 6 Mar 2026 · Technical analysis is probabilistic — not a guarantee of levels

Sheet 🧨 Chambal Fert
B1: CHAMBAL FERTILISERS — TAN PLAY DEEP DIVE
B2: NOT a generic fertiliser stock. A leveraged bet on India mining capex and infrastructure blasting demand.
B4: INVESTMENT CONTEXT
B5: 1. TAN (Technical Ammonium Nitrate) is the principal ingredient in commercial explosives used for mining and infrastructure blasting — not farm fertiliser.
B6: 2. Coal India targets 1 billion MT coal production vs current ~600MT. ~63% of India TAN demand comes from coal mining alone. This is a multi-year structural demand story.
B7: 3. India currently has only 4 domestic TAN producers. Market is structurally undersupplied. Chambal is the 5th entrant — entering with pricing power, not fighting for share.
B8: 4. TAN has NO price cap, NO MRP, NO subsidy dependency. Margins structurally better than urea — a fundamental business model upgrade.
B9: 5. L&T is the EPC contractor. Timeline slip to April 2026 is contractor execution, not a financial or management failure.
B11: CHAMBLFERT — IN PORTFOLIO — HOLD, WAIT FOR TAN REVENUE PRINT
B12: Qty | C12: Avg Cost | D12: CMP | E12: Invested | F12: Mkt Value | G12: P&L | H12: Return | I12: LT Qty
B13: 850 | C13: ₹472.37 | D13: ₹431.30 | E13: ₹401,519 | F13: ₹366,605 | G13: ₹-34,914 | H13: -8.7% | I13: 0
B14: 📌 High conviction TAN play. Plant is 92%+ complete. First revenue in Q1/Q2 FY27 is the catalyst. Well-sized at 5–6% across accounts. Nothing to do but wait.
B15: 🐂 Bull (50%) Target: ₹620–680 | D15: 📊 Base (35%) Target: ₹490–540 | F15: 🐻 Bear (15%) Target: ₹340–370
B16: THE TAN THESIS — WHY THIS IS A DIFFERENT BUSINESS
B17: ✓ TAN plant capacity: 240,000 tonnes. At 80% utilisation × ₹37,000/tonne midpoint = ~₹890Cr TAN revenue alone. Against current total revenue of ~₹18,000Cr — a meaningful margin-accretive addition.
B18: ✓ CRISIL expects non-subsidy business including TAN to contribute over 25% to operating profitability in medium term — structural shift in earnings quality.
B19: ✓ Balance sheet: net cash + liquid investments of ₹800Cr. Zero net debt going into a ₹1,645Cr capex project. This is the right way to do it.
B20: ✓ Base urea business is performing: consolidated operating income +20% YoY in Q3 FY26, +27% for 9M. Net profit +10% and +17% respectively.
B21: ✓ Subsidy receivables comfortable at ₹2,346Cr (Dec 2025). Nil net debt going into a major capex cycle.
B22: ✓ Stock touched ₹654 in April 2025 on TAN expectations. Pulled back with the market. The thesis hasn't changed — the commissioning timeline slipped modestly.
B23: KEY RISKS — WHAT TO WATCH
B24: ✗ Margin compression in urea: EBITDA margins 13.92% in Q3 FY26 vs 15.82% prior year. Input cost (gas prices, ammonia) volatility is the perennial risk.
B25: ✗ Coal India + BHEL JV for 6.6 lakh tonne ammonium nitrate plant in Odisha — large future capacity, but 3–5 years away. Long-term competitive risk.
B26: ✗ Russian TAN imports at competitive prices — a margin ceiling risk for domestic producers.
B27: ✗ Any further delays to TAN commissioning beyond April 2026 would push the catalyst further out.
... B34: → Exit trigger: Commissioning delayed beyond Q2 FY27 without clear explanation, or urea margin compression accelerates beyond 300bps.

Sheet 🏢 EID Parry
B1: EID PARRY — HOLDING COMPANY DEEP DIVE
B2: NOT a sugar company. A deeply discounted proxy on Coromandel International with optionality on nutraceuticals and ethanol.
B4: INVESTMENT CONTEXT
B5: 1. EID Parry is a Murugappa Group holding company. ~90% of SOTP value is the 56% stake in Coromandel International (CRIN) — India's leading crop protection and fertiliser company.
B6: 2. The holdco discount is the entire thesis: EID's market cap trades at 50–60% of the Coromandel stake value alone. You are buying ₹2 of Coromandel for ₹1, plus nutraceuticals and sugar for free.
B7: 3. This discount has persisted for years and could persist for more years. The bet is that it NARROWS from ~55% to ~30% — that gap closure is the entire return.
B8: 4. FII/FPI investor count nearly doubled (393 → 725) in the June 2025 quarter — institutional discovery is beginning. This is what starts to compress a holdco discount.
B9: 5. Murugappa Group is conservative. Do not expect dramatic corporate actions. But even a dividend hike, buyback, or Coromandel re-rating can compress the discount meaningfully.
B11: EIDPARRY — IN PORTFOLIO — HOLD, PATIENCE TRADE | TARGET UP TO 7% ON DIPS
B12: Qty | C12: Avg Cost | D12: CMP | E12: Invested | F12: Mkt Value | G12: P&L | H12: Return | I12: LT Qty
B13: 400 | C13: ₹876.63 | D13: ₹853.90 | E13: ₹350,652 | F13: ₹341,560 | G13: ₹-9,092 | H13: -2.6% | I13: 229
B14: 📌 A patience trade with asymmetric upside if the holdco discount narrows. Not adding aggressively. Would add more if it corrects further — target up to 7%.
B15: 🐂 Bull (40%) Target: ₹2,000–2,500 | D15: 📊 Base (45%) Target: ₹1,100–1,400 | F15: 🐻 Bear (15%) Target: ₹650–750
B16: THE HOLDCO THESIS — WHAT YOU ACTUALLY OWN
B17: ✓ Coromandel International contributed 76% of consolidated revenue and 87% of consolidated net worth in FY25. This is the engine.
B18: ✓ EID holds ~56% of Coromandel. At Coromandel's market cap, EID's stake is worth ₹31,000–38,000Cr. EID's own market cap is a fraction of that — extreme discount.
B19: ✓ SOTP target of ₹2,500 based on ~70% of projected FY28 SOTP reflects discount narrowing from ~60% to ~30%. That single move delivers the return.
B20: ✓ Net cash on EID's balance sheet ₹2,300Cr+. Clean balance sheet. Gradual Coromandel stake sales (0.51% in Feb 2026) are opportunistic for corporate purposes, not distressed selling.
B21: ✓ Nutraceuticals business (spirulina, organic products, US exports) is small but has genuine IP and global market access — systematically undervalued and ignored.
B22: ✓ Sugar/ethanol standalone business is loss-making with a ₹352Cr impairment — but this is already in the price. It's not what you own this for. Ethanol blending policy maturation is a free option.
B23: ✓ FII count doubling in one quarter is a classic early signal of holdco discount re-rating. Institutions are doing the work.
B24: KEY RISKS — WHAT TO WATCH
B25: ✗ Murugappa Group may never act on value unlock. Conservative promoters have let this discount persist for years.
B26: ✗ Coromandel itself faces crop protection cycle risks — if CRIN de-rates, EID's SOTP collapses.
B27: ✗ Gradual stake sales in Coromandel reduce the primary asset over time if not managed carefully.
... B35: → Exit trigger: If Coromandel faces a structural de-rating, re-evaluate SOTP — the discount thesis breaks if the underlying asset is impaired.

Sheet 🏦 Utkarsh SFB
B1: UTKARSH SMALL FINANCE BANK — TURNAROUND DEEP DIVE
B2: Stress was real but geographically concentrated and now visibly inflecting. Smart money in at ₹14. You are too.
B4: INVESTMENT CONTEXT
B5: 1. Utkarsh SFB was hit by simultaneous stress in UP and Bihar MFI portfolios — over 70% of the JLG book originated from these two states. Classic geographic concentration risk playing out.
B6: 2. The promoter "exit" is NOT a red flag — it was a deliberate rights issue renouncement to bring in specific high-quality institutional investors: Madhu Kela (Cohesion MK), India Capital Fund, Kotak Life Insurance, ICICI Prudential Life Insurance.
B7: 3. Rights issue price was ₹14/share. That is your average cost. You are in at the same price as some of the best domestic institutional investors. That is a meaningful anchor.
B8: 4. The key data point: JLG 1-to-90 DPD pool fell from ₹378Cr (Oct 2025) to below ₹50Cr (Jan 2026) — a near-complete clearing of early-stage stress in just 3 months. The inflection is visible and sharp.
B9: 5. Capital adequacy ~20% post rights issue. The bank will not need to raise capital again for the foreseeable future. The loss cycle was front-loaded. Provisions are largely taken.
B11: UTKARSHBNK — IN PORTFOLIO — ACCUMULATE | TARGET 3–4%
B12: Qty | C12: Avg Cost | D12: CMP | E12: Invested | F12: Mkt Value | G12: P&L | H12: Return | I12: LT Qty
B13: 22,000 | C13: ₹14.04 | D13: ₹13.14 | E13: ₹308,812 | F13: ₹289,080 | G13: ₹-19,732 | H13: -6.4% | I13: 0
B14: 📌 Turnaround with strong data backing. Madhu Kela and Kotak Life are in at your price. The asymmetry is good — bear case requires multiple things to go wrong simultaneously.
B15: 🐂 Bull (50%) Target: ₹22–26 | D15: 📊 Base (35%) Target: ₹17–19 | F15: 🐻 Bear (15%) Target: ₹10–11
B16: THE TURNAROUND DATA — WHY THE INFLECTION IS REAL
B17: ✓ JLG DPD pool: ₹378Cr (Oct 2025) → below ₹50Cr (Jan 2026). 87% reduction in 3 months. This is not gradual — it is a step-change clearing.
B18: ✓ Monthly disbursements recovered: ₹800Cr (Oct 2025) → ₹1,200Cr+ (Jan 2026). 50% jump in 3 months. Even the JLG segment started growing again from January after quarters of contraction.
B19: ✓ X-bucket collection efficiency at 99.5% in December 2025 — near-perfect on the performing book.
B20: ✓ Book mix transformation: secured lending now ~50% of loan book vs ~10% in early years. JLG exposure down from ~90% (FY20) to ~33% now. This bank structurally cannot repeat the same stress.
B21: ✓ Rights issue raised ₹950Cr at ₹14/share. Capital adequacy ~20%. No capital raise needed for foreseeable future.
B22: ✓ Investor quality in rights issue: Madhu Kela (Cohesion MK), Kotak Life, ICICI Pru Life, India Capital Fund. These are not passive allocators — they did the work.
B23: ✓ On normalised FY27 PAT of ₹180–200Cr at 1.2–1.5x book = ₹22–26 target. That is 65–100% return from current levels.
B24: KEY RISKS — WHAT TO WATCH
B25: ✗ Second stress wave in UP/Bihar MFI — if rural income shock repeats, provisioning cycle restarts. Monitor quarterly collection efficiency.
B26: ✗ RBI action on SFB licence conditions — regulatory risk always present for small finance banks.
B27: ✗ Macro shock to rural incomes (bad monsoon, commodity price crash) — JLG book still 33% of loans.
... B36: → Exit trigger: second stress wave with DPD pool rising back above ₹150Cr, or RBI action on licence.

Sheet 📝 Changelog
B1: 📝 CHANGELOG — Append one row per session. LLMs: read col D (CHANGE) to understand delta without re-reading whole file.
B3: DATE | C3: SESSION TYPE | D3: CHANGES MADE | E3: STOCKS AFFECTED | F3: PRICES UPDATED | G3: NEXT ACTION
B4: 5 Mar 2026 | C4: Full session | D4: Initial portfolio annotation. 29 holdings mapped. Finance split to 5 sub-sectors. BAJFINANCE avg corrected to ₹660. | E4: All 29 | F4: All CMPs as at 5 Mar 2026 | G4: Consolidation to 25 stocks (Wave 1)
B5: 6 Mar 2026 | C5: Research + thesis update | D5: IEX: changed from TRIM to ACCUMULATE (coupling 18-24m away, vol +30% YoY, tainted CERC). Priority Research updated for top 5. Zydus exit validated. AstraMicro: thesis intact (demerger catalyst added). IT sector deep dive. | E5: IEX, ZYDUSLIFE, ASTRAMICRO, MEDIASSIST, CHAMBLFERT | F5: No price updates | G5: Execute Zydus exit. Monitor MEDIASSIST IRDAI renewal 20 Mar
B6: 7 Mar 2026 | C6: Infrastructure | D6: Added 📥 Price Hub (single CMP source, all sheets now formula-driven). Added 📡 LLM Context sheet. Added 📝 Changelog. Stripped Action Summary number cols (live data in LLM Context). Fixed P&L formatting (green/red, no brackets). Wired Portfolio Brief, Scenario Analysis, Sector Analysis to Price Hub via VLOOKUP/SUMIF. | E6: All (formula wiring) | F6: No CMP changes | G6: Price update: open Price Hub, update col H for each stock
B7: → Add date
B8: → Add date
B9: → Add date
